Workbook

Sheet ASHFORD RESIDENTS ASSOCIATION
B2: John Dickens | C2: jcdickens@talktalk.net | D2: Chairman
B3: Penny Kielty | C3: penny.kielty@hotmail.co.uk | D3: Secretary
B4: Debbie Cousens | C4: debbie.cousens.dc@gmail.com | D4: Treasurer
B6: Committee | C6: =COUNTIF('ALL MEMBERS x1'!J:J,"COMMITTEE") -> 6
B7: Email | C7: =COUNTIF('ALL MEMBERS x1'!J:J,"EMAIL") -> 15
B8: Facebook | C8: =COUNTIF('ALL MEMBERS x1'!J:J,"facebook") -> 10
B9: Fees | C9: =COUNTIF('ALL MEMBERS x1'!J:J,"fees") -> 1
B10: FR&FM | C10: =COUNTIF('ALL MEMBERS x1'!J:J,"FR&FM") -> 4
B11: Leaflet | C11: =COUNTIF('ALL MEMBERS x1'!J:J,"leaflet") -> 10
B12: NextDoor | C12: =COUNTIF('ALL MEMBERS x1'!J:J,"NEXTDOOR") -> 11
B13: NHW | C13: =COUNTIF('ALL MEMBERS x1'!J:J,"NHW") -> 13
B14: PayPal | C14: =COUNTIF('ALL MEMBERS x1'!J:J,"paypal") -> 4
B15: Sign Up Sheet | C15: =COUNTIF('ALL MEMBERS x1'!J:J,"Sign Up Sheet") -> 125
B16: Website | C16: =COUNTIF('ALL MEMBERS x1'!J:J,"WEBSITE") -> 54
B17: Total | C17: =SUM(C6:C16) -> 253
B19: 22nd Feb Meeting | C19: 54 - First Meeting
B20: 14th June Meeting | C20: 100 - Lincoln Jopp / Planning Spaces
B21: 27th Sept Meeting | C21: 130 - HMO Meeting
B22: 24th Jan Meeting | C22: 84 - Police Commissioner
B23: 25th April Meeting | C23: 67 Scams / Healthwatch/Fire Brigade

Sheet Cash
A1: Membership Number | B1: Date | C1: Name | D1: Type | E1: Currency
A2: =_xlfn.XLOOKUP(C2,'ALL MEMBERS x1'!C:C,'ALL MEMBERS x1'!Q:Q) -> 7 | B2: 27/09/2025 | C2: Carol Kielty | D2: Membership Fee | E2: 5
A3: =_xlfn.XLOOKUP(C3,'ALL MEMBERS x1'!C:C,'ALL MEMBERS x1'!Q:Q) -> 75 | B3: 27/09/2025 | C3: John Kielty | D3: Membership Fee | E3: 5
A4: =_xlfn.XLOOKUP(C4,'ALL MEMBERS x1'!C:C,'ALL MEMBERS x1'!Q:Q) -> 228 | B4: 27/09/2025 | C4: Stacy Rielly | D4: Membership Fee | E4: 5
A5: =_xlfn.XLOOKUP(C5,'ALL MEMBERS x1'!C:C,'ALL MEMBERS x1'!Q:Q) -> 22 | B5: 27/09/2025 | C5: Jean Parry | D5: Membership Fee | E5: 5
A6: ='ALL MEMBERS'!A181 -> 180 | B6: 27/09/2025 | C6: Janet O'Brien | D6: Membership Fee | E6: 5
A7: ='ALL MEMBERS'!A208 -> 207 | B7: 27/09/2025 | C7: Jane Whiting | D7: Membership Fee | E7: 5
A8: =_xlfn.XLOOKUP(C8,'ALL MEMBERS x1'!C:C,'ALL MEMBERS x1'!Q:Q) -> 254 | B8: 19/11/2025 | C8: Linda Foster | D8: Membership Fee | E8: 5
A9: =_xlfn.XLOOKUP(C9,'ALL MEMBERS x1'!C:C,'ALL MEMBERS x1'!Q:Q) -> 255 | B9: 26/11/2025 | C9: Rita Robinson | D9: Membership Fee | E9: 5
A10: =_xlfn.XLOOKUP(C10,'ALL MEMBERS x1'!C:C,'ALL MEMBERS x1'!Q:Q) -> 42 | B10: 26/11/2025 | C10: Sheila O'Donovan | D10: Membership Fee | E10: 5
A11: =_xlfn.XLOOKUP(C11,'ALL MEMBERS x1'!C:C,'ALL MEMBERS x1'!Q:Q) -> 197 | B11: 26/11/2025 | C11: Martin Matthews | D11: Membership Fee | E11: 5
A12: =_xlfn.XLOOKUP(C12,'ALL MEMBERS x1'!C:C,'ALL MEMBERS x1'!Q:Q) -> 129 | B12: 45985 | C12: Irene Brien | D12: Donation | E12: 5
A13: ='ALL MEMBERS'!A25 -> 24 | B13: 45994 | C13: John & Angela Burns | D13: Membership Fee | E13: 5
A14: =_xlfn.XLOOKUP(C14,'ALL MEMBERS x1'!C:C,'ALL MEMBERS x1'!Q:Q) -> #NAME? | B14: 46001 | C14: Dennis & Joan Leeks | D14: Membership Fee | E14: 5
A15: =_xlfn.XLOOKUP(C15,'ALL MEMBERS x1'!C:C,'ALL MEMBERS x1'!Q:Q) -> #NAME? | B15: 46001 | C15: Charlotte Pope | D15: Membership Fee | E15: 5
A16: ='ALL MEMBERS'!A259 -> 262 | B16: 46011 | C16: Shyam Petrovini | D16: Membership Fee | E16: 5
A17: =_xlfn.XLOOKUP(C17,'ALL MEMBERS x1'!C:C,'ALL MEMBERS x1'!Q:Q) -> 11 | B17: 46027 | C17: Christine Lloyd | D17: Membership Fee | E17: 5
A18: =_xlfn.XLOOKUP(C18,'ALL MEMBERS x1'!C:C,'ALL MEMBERS x1'!Q:Q) -> 37 | B18: 46029 | C18: Peter Davies | D18: Membership Fee | E18: 5
A19: =_xlfn.XLOOKUP(C19,'ALL MEMBERS x1'!C:C,'ALL MEMBERS x1'!Q:Q) -> 107 | B19: 46032 | C19: Linda Neville | D19: Membership Fee | E19: 5
A20: =_xlfn.XLOOKUP(C20,'ALL MEMBERS x1'!C:C,'ALL MEMBERS x1'!Q:Q) -> 168 | B20: 46032 | C20: Margery Hopkins | D20: Membership Fee | E20: 5
A21: =_xlfn.XLOOKUP(C21,'ALL MEMBERS x1'!C:C,'ALL MEMBERS x1'!Q:Q) -> 110 | B21: 46032 | C21: Mary Freeth | D21: Membership Fee | E21: 5
A22: =_xlfn.XLOOKUP(C22,'ALL MEMBERS x1'!C:C,'ALL MEMBERS x1'!Q:Q) -> 162 | B22: 46032 | C22: June Rubley | D22: Membership Fee | E22: 5
B23: 24/01/2026 | C23: Susan McGee | D23: Membership Fee | E23: 5
B24: 24/01/2026 | C24: Nick Cooper | D24: Membership Fee | E24: 5
B25: 24/01/2026 | C25: Allesandro Benedetto | D25: Membership Fee | E25: 5
B26: 24/01/2026 | C26: Tony Perez | D26: Membership Fee | E26: 5
B27: 46050 | C27: David Wright | D27: Membership Fee | E27: 5
B28: 46133 | C28: Irene Brien | D28: Membership Fee | E28: 5
B29: 46138 | C29: Carol Kielty | D29: Membership Fee | E29: 5
B30: 46138 | C30: John Kielty | D30: Membership Fee | E30: 5
B31: 25/4/2026 | C31: Jackie & Les Brown | D31: Membership Fee | E31: 5
B32: 25/4/2026 | C32: Cathy & Gary Waters | D32: Membership Fee | E32: 5
B33: 25/4/2026 | C33: Annie Sugrue | D33: Membership Fee | E33: 5
B34: 25/4/2026 | C34: Sarah Wrightson | D34: Membership Fee | E34: 5
B35: 25/4/2026 | C35: Debbie Brown | D35: Membership Fee | E35: 5
B36: 25/4/2026 | C36: Pat Jeffcott | D36: Membership Fee | E36: 5
B37: 25/4/2026 | C37: Aash Engineer | D37: Membership Fee | E37: 5
B38: 25/4/2026 | C38: Satpal Thethy | D38: Membership Fee | E38: 5
E44: Gross
C45: Membership Fees | E45: =SUMIF(D:D,"membership fee", E:E) -> 180
C46: Donations | E46: =SUMIF(D:D,"donation", E:E) -> 5
C47: Total | E47: =SUM(E45:E46) -> 185

Sheet PayPal>
A1: Membership Number | B1: Date | C1: Time | D1: Time zone | E1: Name | F1: Type | G1: Status | H1: Currency | I1: Gross | J1: Fee | K1: Net | L1: From Email Address | M1: To Email Address | N1: Transaction ID | O1: Shipping Address | P1: Address Status | Q1: Item Title | R1: Item ID | S1: Postage and Packaging Amount | T1: Insurance Amount | U1: VAT | V1: Option 1 Name | W1: Option 1 Value | X1: Option 2 Name | Y1: Option 2 Value | Z1: Reference Txn ID | AA1: Invoice Number | AB1: Custom Number | AC1: Quantity | AD1: Receipt ID | AE1: Balance | AF1: Address Line 1 | AG1: Address Line 2/District/Neighbourhood | AH1: Town/City | AI1: County | AJ1: Postcode | AK1: Country | AL1: Contact Phone Number | AM1: Subject | AN1: Note | AO1: Country Code | AP1: Balance Impact
A2: =_xlfn.XLOOKUP(E2,'ALL MEMBERS x1'!C:C,'ALL MEMBERS x1'!Q:Q) -> 2 | B2: 20/10/2025 | C2: 0.81527778 | D2: BST | E2: Penny Kielty | F2: Membership Fee | G2: Completed | H2: GBP | I2: 1 | J2: -0.31 | K2: 0.69 | L2: pkielty@cisco.com | M2: treasurer@ashfordra.co.uk | N2: 9FA30462F69560808 | O2: Penny, Kielty, 14 Brownrigg Road, Ashford, Surrey, TW15 2TL, United Kingdom | P2: Confirmed | Q2: Ashford Residents Association | S2: 0 | U2: 0 | AC2: 1 | AD2: 3.4864847e+15 | AE2: 0.69 | AF2: 14 Brownrigg Road | AH2: Ashford | AI2: Surrey | AJ2: TW15 2TL | AK2: United Kingdom | AM2: treasurer@ashfordra.co.uk Ashford Residents Association TW15 | AO2: GB | AP2: Credit
A3: =_xlfn.XLOOKUP(E3,'ALL MEMBERS x1'!C:C,'ALL MEMBERS x1'!Q:Q) -> 2 | B3: 27/10/2025 | C3: 0.47679398 | D3: GMT | E3: Penny Kielty | F3: Membership Fee | G3: Completed | H3: GBP | I3: 5 | J3: -0.36 | K3: 4.64 | L3: pkielty@cisco.com | M3: treasurer@ashfordra.co.uk | N3: 0S346664UW194522E | O3: Penny, Kielty, 14 Brownrigg Road, Ashford, Surrey, TW15 2TL, United Kingdom | P3: Confirmed | Q3: Ashford Residents Association | S3: 0 | U3: 0 | AC3: 1 | AD3: 4.1559093e+15 | AE3: 5.33 | AF3: 14 Brownrigg Road | AH3: Ashford | AI3: Surrey | AJ3: TW15 2TL | AK3: United Kingdom | AM3: treasurer@ashfordra.co.uk Ashford Residents Association TW15 | AO3: GB | AP3: Credit
A4: =_xlfn.XLOOKUP(E4,'ALL MEMBERS x1'!C:C,'ALL MEMBERS x1'!Q:Q) -> 204 | B4: 27/10/2025 | C4: 0.62403935 | D4: GMT | E4: Cara Mackley | F4: Membership Fee | G4: Completed | H4: GBP | I4: 5 | J4: -0.36 | K4: 4.64 | L4: caramackley@icloud.com | M4: treasurer@ashfordra.co.uk | N4: 3JT00745UH3469434 | O4: Cara Mackley, 51, Chesterfield Road, Ashford, Surrey, TW15 2NE, United Kingdom | P4: Confirmed | Q4: Ashford Residents Association | S4: 0 | U4: 0 | AC4: 1 | AD4: 958000000000000 | AE4: 9.97 | AF4: 51 | AG4: Chesterfield Road | AH4: Ashford | AI4: Surrey | AJ4: TW15 2NE | AK4: United Kingdom | AM4: treasurer@ashfordra.co.uk Ashford Residents Association TW15 | AO4: GB | AP4: Credit
A5: =_xlfn.XLOOKUP(E5,'ALL MEMBERS x1'!C:C,'ALL MEMBERS x1'!Q:Q) -> 2 | B5: 27/10/2025 | C5: 0.71159722 | D5: GMT | E5: Penny Kielty | F5: Membership Fee | G5: Completed | H5: GBP | I5: 1 | J5: -0.33 | K5: 0.67 | L5: penny.kielty@hotmail.co.uk | M5: treasurer@ashfordra.co.uk | N5: 17S70426WB198372D | O5: Penny, Kielty, 14 Brownrigg Road, Ashford, Surrey, TW15 2TL, United Kingdom | P5: Confirmed | AE5: 10.64 | AF5: 14 Brownrigg Road | AH5: Ashford | AI5: Surrey | AJ5: TW15 2TL | AK5: United Kingdom | AL5: 7825852680 | AN5: Penny test to treasurer@ashfordra. co. uk £1 | AO5: GB | AP5: Credit
A6: =_xlfn.XLOOKUP(E6,'ALL MEMBERS x1'!C:C,'ALL MEMBERS x1'!Q:Q) -> 2 | B6: 45727 | C6: 0.53766204 | D6: GMT | E6: Penny Kielty | F6: Membership Fee | G6: Completed | H6: GBP | I6: 5 | J6: -0.45 | K6: 4.55 | L6: penny.kielty@hotmail.co.uk | M6: treasurer@ashfordra.co.uk | N6: 65M35095AF569711X | O6: Penny, Kielty, 14 Brownrigg Road, Ashford, Surrey, TW15 2TL, United Kingdom | P6: Confirmed | AE6: 15.19 | AF6: 14 Brownrigg Road | AH6: Ashford | AI6: Surrey | AJ6: TW15 2TL | AK6: United Kingdom | AL6: 7825852680 | AN6: Penny Test PAYPAL email | AO6: GB | AP6: Credit
A7: =_xlfn.XLOOKUP(E7,'ALL MEMBERS x1'!C:C,'ALL MEMBERS x1'!Q:Q) -> 2 | B7: 45788 | C7: 0.73603009 | D7: GMT | E7: Penny Kielty | F7: Membership Fee | G7: Completed | H7: GBP | I7: 1 | J7: -0.31 | K7: 0.69 | L7: pkielty@cisco.com | M7: treasurer@ashfordra.co.uk | N7: 7JN969183R571572C | O7: Penny, Kielty, 14 Brownrigg Road, Ashford, Surrey, TW15 2TL, United Kingdom | P7: Confirmed | Q7: Ashford Residents Association Membership | S7: 0 | U7: 0 | AC7: 1 | AD7: 1.0676841e+15 | AE7: 15.88 | AF7: 14 Brownrigg Road | AH7: Ashford | AI7: Surrey | AJ7: TW15 2TL | AK7: United Kingdom | AM7: treasurer@ashfordra.co.uk Household Membership Fee Payment Link Ashford Residents Association (ARA TW15) | AO7: GB | AP7: Credit
A8: =_xlfn.XLOOKUP(E8,'ALL MEMBERS x1'!C:C,'ALL MEMBERS x1'!Q:Q) -> 2 | B8: 45788 | C8: 0.73768519 | D8: GMT | E8: Penny Kielty | F8: Membership Fee | G8: Completed | H8: GBP | I8: 1 | J8: -0.31 | K8: 0.69 | L8: pkielty@cisco.com | M8: treasurer@ashfordra.co.uk | N8: 5EY42286AL899450S | O8: Penny, Kielty, 14 Brownrigg Road, Ashford, Surrey, TW15 2TL, United Kingdom | P8: Confirmed | Q8: Ashford Residents Association Donation | S8: 0 | U8: 0 | V8: We would love to say thank you - Please leave your comments and | W8: Penny test donation | AC8: 1 | AD8: 925000000000000 | AE8: 16.57 | AF8: 14 Brownrigg Road | AH8: Ashford | AI8: Surrey | AJ8: TW15 2TL | AK8: United Kingdom | AM8: treasurer@ashfordra.co.uk Donations Payment Link Ashford Residents Association (ARA TW15) | AO8: GB | AP8: Credit
A9: =_xlfn.XLOOKUP(E9,'ALL MEMBERS x1'!C:C,'ALL MEMBERS x1'!Q:Q) -> 253 | B9: 13/11/2025 | C9: 0.37459491 | D9: GMT | E9: Kevin Wise | F9: Membership Fee | G9: Completed | H9: GBP | I9: 5 | J9: -0.45 | K9: 4.55 | L9: kp_wise@hotmail.com | M9: treasurer@ashfordra.co.uk | N9: 0UA61825XW803534N | O9: Kevin, Wise, 15 Meadow Road, Ashford, Middlesex, TW15 1PL, United Kingdom | P9: Confirmed | AE9: 21.12 | AF9: 15 Meadow Road | AH9: Ashford | AI9: Middlesex | AJ9: TW15 1PL | AK9: United Kingdom | AL9: 7795172052 | AO9: GB | AP9: Credit
A10: =_xlfn.XLOOKUP(E10,'ALL MEMBERS x1'!C:C,'ALL MEMBERS x1'!Q:Q) -> 2 | B10: 15/11/2025 | C10: 0.92210648 | D10: GMT | E10: Penny Kielty | F10: Membership Fee | G10: Completed | H10: GBP | I10: 1 | J10: -0.33 | K10: 0.67 | L10: penny.kielty@hotmail.co.uk | M10: treasurer@ashfordra.co.uk | N10: 16W55236SV035011N | O10: Penny, Kielty, 14 Brownrigg Road, Ashford, Surrey, TW15 2TL, United Kingdom | P10: Confirmed | AE10: 21.79 | AF10: 14 Brownrigg Road | AH10: Ashford | AI10: Surrey | AJ10: TW15 2TL | AK10: United Kingdom | AL10: 7825852680 | AN10: Test new link Penny | AO10: GB | AP10: Credit
A11: =_xlfn.XLOOKUP(E11,'ALL MEMBERS x1'!C:C,'ALL MEMBERS x1'!Q:Q) -> 2 | B11: 15/11/2025 | C11: 0.93003472 | D11: GMT | E11: Penny Kielty | F11: Membership Fee | G11: Completed | H11: GBP | I11: 1 | J11: -0.31 | K11: 0.69 | L11: pkielty@cisco.com | M11: treasurer@ashfordra.co.uk | N11: 9M784616CB539194V | O11: Penny, Kielty, 14 Brownrigg Road, Ashford, Surrey, TW15 2TL, United Kingdom | P11: Confirmed | Q11: Ashford Residents Association Membership | S11: 0 | U11: 0 | AC11: 1 | AD11: 5.5412443e+15 | AE11: 22.48 | AF11: 14 Brownrigg Road | AH11: Ashford | AI11: Surrey | AJ11: TW15 2TL | AK11: United Kingdom | AM11: treasurer@ashfordra.co.uk Household Membership Fee Payment Link Ashford Residents Association (ARA TW15) | AO11: GB | AP11: Credit
A12: =_xlfn.XLOOKUP(E12,'ALL MEMBERS x1'!C:C,'ALL MEMBERS x1'!Q:Q) -> 2 | B12: 15/11/2025 | C12: 0.93085648 | D12: GMT | E12: Penny Kielty | F12: Membership Fee | G12: Completed | H12: GBP | I12: 1 | J12: -0.33 | K12: 0.67 | L12: penny.kielty@hotmail.co.uk | M12: treasurer@ashfordra.co.uk | N12: 1XG21341VH038212B | O12: Penny, Kielty, 14 Brownrigg Road, Ashford, Surrey, TW15 2TL, United Kingdom | P12: Confirmed | AE12: 23.15 | AF12: 14 Brownrigg Road | AH12: Ashford | AI12: Surrey | AJ12: TW15 2TL | AK12: United Kingdom | AL12: 7825852680 | AN12: Another test PayPal | AO12: GB | AP12: Credit
A13: =_xlfn.XLOOKUP(E13,'ALL MEMBERS x1'!C:C,'ALL MEMBERS x1'!Q:Q) -> 242 | B13: 23/11/2025 | C13: 0.90726852 | D13: GMT | E13: Ursula Wnuk | F13: Membership Fee | G13: Completed | H13: GBP | I13: 5 | J13: -0.45 | K13: 4.55 | L13: uhill@hotmail.com | M13: treasurer@ashfordra.co.uk | N13: 56758645TS4909520 | O13: Ursula, Wnuk, 100 Village Way, ASHFORD, Middlesex, TW15 2JU, United Kingdom | P13: Unconfirmed | AE13: 27.7 | AF13: 100 Village Way | AH13: ASHFORD | AI13: Middlesex | AJ13: TW15 2JU | AK13: United Kingdom | AL13: 7890000000 | AO13: GB | AP13: Credit
A14: =_xlfn.XLOOKUP(E14,'ALL MEMBERS x1'!C:C,'ALL MEMBERS x1'!Q:Q) -> 130 | B14: 23/11/2025 | C14: 0.91950231 | D14: GMT | E14: Mary Sansom | F14: Membership Fee | G14: Completed | H14: GBP | I14: 5 | J14: -0.45 | K14: 4.55 | L14: maryebay3349@gmail.com | M14: treasurer@ashfordra.co.uk | N14: 7VF96625N1572241Y | O14: Mary, Sansom, 33 Fontmell park, Ashford, Middlesex, TW152NP, United Kingdom | P14: Confirmed | AE14: 32.25 | AF14: 33 Fontmell park | AH14: Ashford | AI14: Middlesex | AJ14: TW152NP | AK14: United Kingdom | AL14: 7920000000 | AN14: from : Mary Sansom. 33 Fontmell Park. Ashford. TW15 2NP | AO14: GB | AP14: Credit
A15: =_xlfn.XLOOKUP(E15,'ALL MEMBERS x1'!C:C,'ALL MEMBERS x1'!Q:Q) -> 251 | B15: 23/11/2025 | C15: 0.96206019 | D15: GMT | E15: Kay Hennah | F15: Membership Fee | G15: Completed | H15: GBP | I15: 5 | J15: -0.36 | K15: 4.64 | L15: kay.hennah@talktalk.net | M15: treasurer@ashfordra.co.uk | N15: 7SE61644J81128054 | O15: Kay, Hennah, 1 Dorset Road, Ashford, MIDDLESEX, TW15 3BZ, United Kingdom | P15: Confirmed | Q15: Ashford Residents Association Membership | S15: 0 | U15: 0 | AC15: 1 | AD15: 5.5e+15 | AE15: 36.89 | AF15: 1 Dorset Road | AH15: Ashford | AI15: MIDDLESEX | AJ15: TW15 3BZ | AK15: United Kingdom | AM15: treasurer@ashfordra.co.uk Household Membership Fee Payment Link Ashford Residents Association (ARA TW15) | AO15: GB | AP15: Credit
A16: =_xlfn.XLOOKUP(E16,'ALL MEMBERS x1'!C:C,'ALL MEMBERS x1'!Q:Q) -> 56 | B16: 24/11/2025 | C16: 0.59204861 | D16: GMT | E16: John Swaffield | F16: Membership Fee | G16: Completed | H16: GBP | I16: 5 | J16: -0.45 | K16: 4.55 | L16: swaffield@btinternet.com | M16: treasurer@ashfordra.co.uk | N16: 0D944531WX6483406 | O16: john, swaffield, 51 stanwell rd, ashford, Middlesex, TW15 3EH, United Kingdom | P16: Unconfirmed | AE16: 41.44 | AF16: 51 stanwell rd | AH16: ashford | AI16: Middlesex | AJ16: TW15 3EH | AK16: United Kingdom | AL16: 7870000000 | AO16: GB | AP16: Credit
A17: =_xlfn.XLOOKUP(E17,'ALL MEMBERS x1'!C:C,'ALL MEMBERS x1'!Q:Q) -> 200 | B17: 24/11/2025 | C17: 0.6325 | D17: GMT | E17: Ann Robinson | F17: Membership Fee | G17: Completed | H17: GBP | I17: 5 | J17: -0.36 | K17: 4.64 | L17: schezanne@talktalk.net | M17: treasurer@ashfordra.co.uk | N17: 48G58287XB312014G | O17: Ann, Robinson, 88 Ashgrove Road, Ashford, ENGLAND, TW15 1PD, United Kingdom | P17: Confirmed | Q17: Ashford Residents Association Membership | S17: 0 | U17: 0 | AC17: 1 | AD17: 369000000000000 | AE17: 46.08 | AF17: 88 Ashgrove Road | AH17: Ashford | AI17: ENGLAND | AJ17: TW15 1PD | AK17: United Kingdom | AM17: treasurer@ashfordra.co.uk Household Membership Fee Payment Link Ashford Residents Association (ARA TW15) | AO17: GB | AP17: Credit
A18: =_xlfn.XLOOKUP(E18,'ALL MEMBERS x1'!C:C,'ALL MEMBERS x1'!Q:Q) -> 111 | B18: 24/11/2025 | C18: 0.66168981 | D18: GMT | E18: Nicola Streeter | F18: Membership Fee | G18: Completed | H18: GBP | I18: 5 | J18: -0.45 | K18: 4.55 | L18: ickle_nik@yahoo.com | M18: treasurer@ashfordra.co.uk | N18: 5W005233BG395183J | O18: Nicola, Streeter, 11 Chester Close, Ashford, MIDDLESEX, TW15 1PH, United Kingdom | P18: Unconfirmed | AE18: 50.63 | AF18: 11 Chester Close | AH18: Ashford | AI18: MIDDLESEX | AJ18: TW15 1PH | AK18: United Kingdom | AL18: 7870000000 | AN18: Nicola Streeter | AO18: GB | AP18: Credit
A19: =_xlfn.XLOOKUP(E19,'ALL MEMBERS x1'!C:C,'ALL MEMBERS x1'!Q:Q) -> 239 | B19: 24/11/2025 | C19: 0.69071759 | D19: GMT | E19: Paul Cousens | F19: Membership Fee | G19: Completed | H19: GBP | I19: 5 | J19: -0.45 | K19: 4.55 | L19: pcousens@sky.com | M19: treasurer@ashfordra.co.uk | N19: 5S343755KP074482S | O19: Paul, Cousens, 64 Gordon Road, Ashford, MIDDLESEX, TW15 3EU, United Kingdom | P19: Unconfirmed | AE19: 55.18 | AF19: 64 Gordon Road | AH19: Ashford | AI19: MIDDLESEX | AJ19: TW15 3EU | AK19: United Kingdom | AL19: 7830000000 | AO19: GB | AP19: Credit
A20: =_xlfn.XLOOKUP(E20,'ALL MEMBERS x1'!C:C,'ALL MEMBERS x1'!Q:Q) -> 67 | B20: 24/11/2025 | C20: 0.77488426 | D20: GMT | E20: Melanie Hughes | F20: Membership Fee | G20: Completed | H20: GBP | I20: 5 | J20: -0.45 | K20: 4.55 | L20: meljane224@yahoo.co.uk | M20: treasurer@ashfordra.co.uk | N20: 6924827091372325E | O20: melanie, hughes, Pippin Cottage 7, chesterfield road, ASHFORD, TW15 2NB, United Kingdom | P20: Unconfirmed | AE20: 59.73 | AF20: Pippin Cottage 7 | AG20: chesterfield road | AH20: ASHFORD | AJ20: TW15 2NB | AK20: United Kingdom | AL20: 1780000000 | AN20: I'm so sorry it's taken so long to pay, I completely forgot. | AO20: GB | AP20: Credit
A21: =_xlfn.XLOOKUP(E21,'ALL MEMBERS x1'!C:C,'ALL MEMBERS x1'!Q:Q) -> 93 | B21: 24/11/2025 | C21: 0.8225463 | D21: GMT | E21: Nabila Ritchie | F21: Membership Fee | G21: Completed | H21: GBP | I21: 5 | J21: -0.45 | K21: 4.55 | L21: nabila_ritchie@hotmail.com | M21: treasurer@ashfordra.co.uk | N21: 6NU79871HE9237224 | O21: Nabila, Ritchie, 154B Feltham Rd, Ashford, MIDDLESEX, TW15 1AD, United Kingdom | P21: Unconfirmed | AE21: 64.28 | AF21: 154B Feltham Rd | AH21: Ashford | AI21: MIDDLESEX | AJ21: TW15 1AD | AK21: United Kingdom | AL21: 7750000000 | AN21: My apologies - did not realise there was a fee to pay. | AO21: GB | AP21: Credit
A22: =_xlfn.XLOOKUP(E22,'ALL MEMBERS x1'!C:C,'ALL MEMBERS x1'!Q:Q) -> 14 | B22: 24/11/2025 | C22: 0.93418981 | D22: GMT | E22: David Lee | F22: Membership Fee | G22: Completed | H22: GBP | I22: 5 | J22: -0.45 | K22: 4.55 | L22: madlee01@yahoo.co.uk | M22: treasurer@ashfordra.co.uk | N22: 8MH14668DS404573C | O22: David, Lee, 12 Gordon Rd, Ashford, Middlesex, TW15 3EU, United Kingdom | P22: Unconfirmed | AE22: 68.83 | AF22: 12 Gordon Rd | AH22: Ashford | AI22: Middlesex | AJ22: TW15 3EU | AK22: United Kingdom | AL22: 7850000000 | AN22: Subscription from David Lee 12 Gordon Road Ashford TW15 3EU | AO22: GB | AP22: Credit
A23: =_xlfn.XLOOKUP(E23,'ALL MEMBERS x1'!C:C,'ALL MEMBERS x1'!Q:Q) -> 163 | B23: 25/11/2025 | C23: 0.70212963 | D23: GMT | E23: Kathleen Marshall | F23: Membership Fee | G23: Completed | H23: GBP | I23: 5 | J23: -0.45 | K23: 4.55 | L23: kmarshall1945@talktalk.net | M23: treasurer@ashfordra.co.uk | N23: 2K868097UH169184Y | O23: Kathleen, Marshall, 53 Feltham Road, Ashford, MIDDLESEX, TW15 1DQ, United Kingdom | P23: Unconfirmed
A24: =_xlfn.XLOOKUP(E24,'ALL MEMBERS x1'!C:C,'ALL MEMBERS x1'!Q:Q) -> 2 | B24: 29/11/2025 | C24: 0.69332176 | D24: GMT | E24: Penny Kielty | F24: Membership Fee | G24: Completed | H24: GBP | I24: 1 | J24: -0.31 | K24: 0.69 | L24: penny.kielty@gmail.com | M24: treasurer@ashfordra.co.uk | N24: 4VB7239908061024V | O24: Penny, Kielty, 14 Brownrigg Road, Ashford, MIDDLESEX, TW15 2TL, United Kingdom | P24: Confirmed
A25: =_xlfn.XLOOKUP(E25,'ALL MEMBERS x1'!C:C,'ALL MEMBERS x1'!Q:Q) -> 2 | B25: 29/11/2025 | C25: 0.69429398 | D25: GMT | E25: Penny Kielty | F25: Membership Fee | G25: Completed | H25: GBP | I25: 1 | J25: -0.33 | K25: 0.67 | L25: penny.kielty@hotmail.co.uk | M25: treasurer@ashfordra.co.uk | N25: 13V267241G346970D | O25: Penny, Kielty, 14 Brownrigg Road, Ashford, Surrey, TW15 2TL, United Kingdom | P25: Confirmed
A26: =_xlfn.XLOOKUP(E26,'ALL MEMBERS x1'!C:C,'ALL MEMBERS x1'!Q:Q) -> 2 | B26: 29/11/2025 | C26: 0.71659722 | D26: GMT | E26: Penny Kielty | F26: Membership Fee | G26: Completed | H26: GBP | I26: 1 | J26: -0.33 | K26: 0.67 | L26: penny.kielty@hotmail.co.uk | M26: treasurer@ashfordra.co.uk | N26: 3XM945832L408781J | O26: Penny, Kielty, 14 Brownrigg Road, Ashford, Surrey, TW15 2TL, United Kingdom | P26: Confirmed
A27: =_xlfn.XLOOKUP(E27,'ALL MEMBERS x1'!C:C,'ALL MEMBERS x1'!Q:Q) -> 142 | B27: 30/11/2025 | C27: 0.45159722 | D27: GMT | E27: Linda Lawrie | F27: Membership Fee | G27: Completed | H27: GBP | I27: 5 | J27: -0.36 | K27: 4.64 | L27: lindajslawrie@sky.com | M27: treasurer@ashfordra.co.uk | N27: 0XP97871BJ5348128 | O27: Linda, Lawrie, 2 Grays Lane, Ashford, SURREY, TW15 1BY, United Kingdom | P27: Confirmed
A28: =_xlfn.XLOOKUP(E28,'ALL MEMBERS x1'!C:C,'ALL MEMBERS x1'!Q:Q) -> #N/A | B28: 45991 | C28: 0.55622685 | D28: GMT | E28: david collis | F28: Membership Fee | G28: Completed | H28: GBP | I28: 5 | J28: -0.45 | K28: 4.55 | L28: Collid2@virginmedia.com | M28: treasurer@ashfordra.co.uk | N28: 74S177940L0887909 | O28: david, collis, 60 CHAUCER RD, ASHFORD, Middlesex, TW152QX, United Kingdom | P28: Unconfirmed
A29: =_xlfn.XLOOKUP(E29,'ALL MEMBERS x1'!C:C,'ALL MEMBERS x1'!Q:Q) -> 100 | B29: 45993 | C29: 0.70425926 | D29: GMT | E29: ANDREW WILLIAMS | F29: Membership Fee | G29: Completed | H29: GBP | I29: 5 | J29: -0.45 | K29: 4.55 | L29: andywilliams290@hotmail.com | M29: treasurer@ashfordra.co.uk | N29: 4SL368895D821570B | O29: ANDREW, WILLIAMS, 30, ASHGROVE RD, ASHFORD, Middlesex, TW151NU, United Kingdom | P29: Confirmed | AO29: GB | AP29: Credit
A30: =_xlfn.XLOOKUP(E30,'ALL MEMBERS x1'!C:C,'ALL MEMBERS x1'!Q:Q) -> 238 | B30: 45759 | C30: 0.94505787 | D30: GMT | E30: Panagiota Mavrigiannaki | F30: Membership Fee | G30: Completed | H30: GBP | I30: 5 | J30: -0.36 | K30: 4.64 | L30: foxoriginal@hotmail.com | M30: treasurer@ashfordra.co.uk | N30: 3CE45314V4630344J | O30: Panagiota, Mavrigiannaki, 35 Fernhurst Road, Ashford, SURREY, TW15 1AQ, United Kingdom | P30: Confirmed | Q30: Ashford Residents Association Membership | S30: 0 | U30: 0 | AC30: 1 | AD30: 5.01e+15 | AE30: 93.79 | AF30: 35 Fernhurst Road | AH30: Ashford | AI30: SURREY | AJ30: TW15 1AQ | AK30: United Kingdom | AM30: treasurer@ashfordra.co.uk Household Membership Fee Payment Link Ashford Residents Association (ARA TW15) | AO30: GB | AP30: Credit
A31: ='ALL MEMBERS'!A194 -> 193 | B31: 45912 | C31: 0.91173611 | D31: GMT | E31: Mike Keegan | F31: Membership Fee | G31: Completed | H31: GBP | I31: 5 | J31: -0.45 | K31: 4.55 | L31: keeganuk07@outlook.com | M31: treasurer@ashfordra.co.uk | N31: 5KC436944T7466519 | O31: Mike, Keegan, 8 Mornington Road, Ashford, Middlesex, tw151nw, United Kingdom | P31: Unconfirmed | AE31: 98.34 | AF31: 8 Mornington Road | AH31: Ashford | AI31: Middlesex | AJ31: tw151nw | AK31: United Kingdom | AL31: 7900000000 | AO31: GB | AP31: Credit
A32: =_xlfn.XLOOKUP(E32,'ALL MEMBERS x1'!C:C,'ALL MEMBERS x1'!Q:Q) -> 85 | B32: 45942 | C32: 0.45405093 | D32: GMT | E32: Neeraj Wadhwa | F32: Membership Fee | G32: Completed | H32: GBP | I32: 5 | J32: -0.45 | K32: 4.55 | L32: Wadhwaneeraj20@gmail.com | M32: treasurer@ashfordra.co.uk | N32: 87S90373P3746883D | O32: Neeraj, Wadhwa, 13 pear Tree Road, Ashford, TW151PW, United Kingdom | P32: Unconfirmed | AE32: 102.89 | AF32: 13 pear Tree Road | AH32: Ashford | AJ32: TW151PW | AK32: United Kingdom | AL32: 7890000000 | AN32: Ashford residents association memebership - Neeraj W | AO32: GB | AP32: Credit
A33: =_xlfn.XLOOKUP(E33,'ALL MEMBERS x1'!C:C,'ALL MEMBERS x1'!Q:Q) -> 137 | B33: 45942 | C33: 0.5140162 | D33: GMT | E33: Sonjoy Premi | F33: Membership Fee | G33: Completed | H33: GBP | I33: 5 | J33: -0.45 | K33: 4.55 | L33: sonjoy@future-computing.co.uk | M33: treasurer@ashfordra.co.uk | N33: 67Y637071G864100C | O33: Sonjoy, Premi, 70 village way, ashford, Middlesex, tw152lb, United Kingdom | P33: Unconfirmed | AE33: 107.44 | AF33: 70 village way | AH33: ashford | AI33: Middlesex | AJ33: tw152lb | AK33: United Kingdom | AL33: 7800000000 | AN33: Hello, sending you Ashford RA annual membership payment of £5 for 70 Village Way. Our names are Dr Sonjoy Kumar Premi and Mrs Sunanda Premi | AO33: GB | AP33: Credit
A34: =_xlfn.XLOOKUP(E34,'ALL MEMBERS x1'!C:C,'ALL MEMBERS x1'!Q:Q) -> 250 | B34: 45942 | C34: 0.57998843 | D34: GMT | E34: Christopher Salomons | F34: Membership Fee | G34: Completed | H34: GBP | I34: 5 | J34: 0 | K34: 5 | L34: c_salomons@hotmail.com | M34: treasurer@ashfordra.co.uk | N34: 5TK20869EL039160X | P34: Unconfirmed | AE34: 112.44 | AL34: 7960000000 | AN34: Salomons - 25 Coleridge Road | AP34: Credit
A35: =_xlfn.XLOOKUP(E35,'ALL MEMBERS x1'!C:C,'ALL MEMBERS x1'!Q:Q) -> 4 | B35: 45942 | C35: 0.64184028 | D35: GMT | E35: Andrew Lewis | F35: Membership Fee | G35: Completed | H35: GBP | I35: 5 | J35: -0.36 | K35: 4.64 | L35: denandlewis@gmail.com | M35: treasurer@ashfordra.co.uk | N35: 68K53291NF592714T | O35: Andrew, Lewis, 4 Ford Close, Ashford, MIDDLESEX, TW15 3SB, United Kingdom | P35: Confirmed | Q35: Ashford Residents Association Membership | S35: 0 | U35: 0 | AC35: 1 | AD35: 3.3e+15 | AE35: 117.08 | AF35: 4 Ford Close | AH35: Ashford | AI35: MIDDLESEX | AJ35: TW15 3SB | AK35: United Kingdom | AM35: treasurer@ashfordra.co.uk Household Membership Fee Payment Link Ashford Residents Association (ARA TW15) | AO35: GB | AP35: Credit
A36: =_xlfn.XLOOKUP(E36,'ALL MEMBERS x1'!C:C,'ALL MEMBERS x1'!Q:Q) -> 12 | B36: 45942 | C36: 0.67179398 | D36: GMT | E36: Christine Wooster | F36: Membership Fee | G36: Completed | H36: GBP | I36: 5 | J36: -0.45 | K36: 4.55 | L36: chris.wooster@btinternet.com | M36: treasurer@ashfordra.co.uk | N36: 7YC26019J30397259 | O36: Christine, Wooster, 19 Percy Avenue, Ashford, Middlesex, TW15 2PB, United Kingdom | P36: Unconfirmed | AE36: 121.63 | AF36: 19 Percy Avenue | AH36: Ashford | AI36: Middlesex | AJ36: TW15 2PB | AK36: United Kingdom | AL36: 7920000000 | AN36: Chris Wooster 19 Percy Avenue | AO36: GB | AP36: Credit
A37: =_xlfn.XLOOKUP(E37,'ALL MEMBERS x1'!C:C,'ALL MEMBERS x1'!Q:Q) -> 38 | B37: 46003 | C37: 0.74684028 | D37: GMT | E37: Phil Henley | F37: Membership Fee | G37: Completed | H37: GBP | I37: 5 | J37: -0.45 | K37: 4.55 | L37: peehen@talk21.com | M37: treasurer@ashfordra.co.uk | N37: 4XT868374X091515J | O37: Phil, Henley, 62 Village Way, Ashford, TW152LB, United Kingdom | P37: Unconfirmed | AE37: 126.18 | AF37: 62 Village Way | AH37: Ashford | AJ37: TW152LB | AK37: United Kingdom | AL37: 7880000000 | AN37: Phil Henley | AO37: GB | AP37: Credit
A38: =_xlfn.XLOOKUP(E38,'ALL MEMBERS x1'!C:C,'ALL MEMBERS x1'!Q:Q) -> 81 | B38: 46003 | C38: 0.85552083 | D38: GMT | E38: John Wasley | F38: Membership Fee | G38: Completed | H38: GBP | I38: 5 | J38: -0.45 | K38: 4.55 | L38: jwasley408@googlemail.com | M38: treasurer@ashfordra.co.uk | N38: 9AX045092W1534719 | O38: John, Wasley, 86 Chesterfield Road, Ashford, Ashford, MIDDLESEX, TW152ND, United Kingdom | P38: Confirmed | Q38: Ashford Residents Association Membership | S38: 0 | U38: 0 | AC38: 1 | AE38: 130.73 | AF38: 86 Chesterfield Road | AG38: Ashford | AH38: Ashford | AI38: MIDDLESEX | AJ38: TW152ND | AK38: United Kingdom | AL38: 7520000000 | AM38: treasurer@ashfordra.co.uk Household Membership Fee Payment Link Ashford Residents Association (ARA TW15) | AO38: GB | AP38: Credit
B39: 28/12/2025 | C39: 0.87304398 | D39: GMT | E39: Jenny Frost | F39: Membership Fee | G39: Completed | H39: GBP | I39: 10 | J39: -0.42 | K39: 9.58 | L39: jenny@lomas.uk | M39: treasurer@ashfordra.co.uk | N39: 7Y2043700L147973W | O39: Jenny Frost, 45 Clarendon Road, Ashford, England, TW15 2QA, United Kingdom | P39: Confirmed | Q39: Ashford Residents Association Membership | S39: 0 | U39: 0 | AC39: 1 | AD39: 4.6905659e+15 | AE39: 140.31 | AF39: 45 Clarendon Road | AH39: Ashford | AI39: England | AJ39: TW15 2QA | AK39: United Kingdom | AM39: treasurer@ashfordra.co.uk Household Membership Fee Payment Link Ashford Residents Association (ARA TW15) | AO39: GB | AP39: Credit
B40: 46143 | C40: 0.36206019 | D40: GMT | E40: Anita Mckenzie | F40: Membership Fee | G40: Completed | H40: GBP | I40: 5 | J40: -0.36 | K40: 4.64 | L40: greouxaquae@icloud.com | M40: treasurer@ashfordra.co.uk | N40: 0AT912558C4448545 | O40: Anita, Mckenzie, 39 Manor Roaf, Ashford, Ashford, MIDDLESEX, TW15 2SL, United Kingdom | P40: Confirmed | Q40: Ashford Residents Association Membership | S40: 0 | U40: 0 | AC40: 1 | AD40: 556000000000000 | AE40: 144.95 | AF40: 39 Manor Road | AG40: Ashford | AH40: Ashford | AI40: MIDDLESEX | AJ40: TW15 2SL | AK40: United Kingdom | AM40: treasurer@ashfordra.co.uk Household Membership Fee Payment Link Ashford Residents Association (ARA TW15) | AO40: GB | AP40: Credit
B41: 46296 | C41: 0.39084491 | D41: GMT | E41: Tracy Brown | F41: Membership Fee | G41: Completed | H41: GBP | I41: 5 | J41: -0.45 | K41: 4.55 | L41: tracy.j.brown@talk21.com | M41: treasurer@ashfordra.co.uk | N41: 0LC96835YT974583V | O41: Tracy, Brown, 41 Station Crescent, Ashford, Middlesex, TW15 3HX, United Kingdom | P41: Confirmed | AE41: 149.5 | AF41: 41 Station Crescent | AH41: Ashford | AI41: Middlesex | AJ41: TW15 3HX | AK41: United Kingdom | AL41: 7850000000 | AN41: Membership fee Martyn Brown | AO41: GB | AP41: Credit
B42: 25/01/2026 | C42: 0.64125 | D42: GMT | E42: Julie Holman | F42: Donation | G42: Completed | H42: GBP | I42: 10 | J42: -0.42 | K42: 9.58 | L42: julesaholman@gmail.com | M42: treasurer@ashfordra.co.uk | N42: 4A632793590490741 | O42: Julie, Holman, 30 Rex Ave, Ashford, TW15 2DA, United Kingdom | P42: Confirmed | Q42: Ashford Residents Association Membership | S42: 0 | U42: 0 | AC42: 1 | AD42: 394000000000000 | AE42: 159.08 | AF42: 30 Rex Ave | AH42: Ashford | AJ42: TW15 2DA | AK42: United Kingdom | AM42: treasurer@ashfordra.co.uk Household Membership Fee Payment Link Ashford Residents Association (ARA TW15) | AO42: GB | AP42: Credit
B43: 16/02/2026 | C43: 0.71710648 | D43: GMT | E43: Clare Sabiston | F43: Membership Fee | G43: Completed | H43: GBP | I43: 5 | J43: -0.36 | K43: 4.64 | L43: clareclareclares@gmail.com | M43: treasurer@ashfordra.co.uk | N43: 6L40807294800393T | O43: Clare Sabiston, 26A Church Road, Ashford, Spelthorne, England, TW15 2UY, United Kingdom | P43: Confirmed | Q43: Ashford Residents Association Membership | S43: 0 | U43: 0 | AC43: 1 | AD43: 2.53e+15 | AE43: 163.72 | AF43: 26A Church Road | AG43: Ashford | AH43: Spelthorne | AI43: England | AJ43: TW15 2UY | AK43: United Kingdom | AM43: treasurer@ashfordra.co.uk Household Membership Fee Payment Link Ashford Residents Association (ARA TW15) | AO43: GB | AP43: Credit
B44: 17/02/2026 | C44: 0.49695602 | D44: GMT | E44: David Speakman | F44: Membership Fee | G44: Completed | H44: GBP | I44: 5 | J44: -0.36 | K44: 4.64 | L44: matthewspeakman712@gmail.com | M44: treasurer@ashfordra.co.uk | N44: 1XY30617CU647632R | O44: David, Speakman, 205, Feltham Road, Ashford, MIDDLESEX, TW15 1BB, United Kingdom | P44: Confirmed | Q44: Ashford Residents Association Membership | S44: 0 | U44: 0 | AC44: 1 | AD44: 3.36e+15 | AE44: 168.36 | AF44: 205 | AG44: Feltham Road | AH44: Ashford | AI44: MIDDLESEX | AJ44: TW15 1BB | AK44: United Kingdom | AM44: treasurer@ashfordra.co.uk Household Membership Fee Payment Link Ashford Residents Association (ARA TW15) | AO44: GB | AP44: Credit
B45: 18/02/2026 | C45: 0.50989583 | D45: GMT | E45: Val Clark | F45: Membership Fee | G45: Completed | H45: GBP | I45: 5 | J45: -0.36 | K45: 4.64 | L45: clarkvandm@yahoo.co.uk | M45: treasurer@ashfordra.co.uk | N45: 2JT64886EM413402L | O45: Val, Clark, 12 Ferndale Road, Ashford, MIDDLESEX, TW15 3PJ, United Kingdom | P45: Confirmed | Q45: Ashford Residents Association Membership | S45: 0 | U45: 0 | AC45: 1 | AD45: 763000000000000 | AE45: 173 | AF45: 12 Ferndale Road | AH45: Ashford | AI45: MIDDLESEX | AJ45: TW15 3PJ | AK45: United Kingdom | AM45: treasurer@ashfordra.co.uk Household Membership Fee Payment Link Ashford Residents Association (ARA TW15) | AO45: GB | AP45: Credit
B46: 21/03/2026 | C46: 0.58856481 | D46: GMT | E46: Susan Goddard | F46: Membership Fee | G46: Completed | H46: GBP | I46: 5 | J46: -0.45 | K46: 4.55 | L46: sue.goddard14@outlook.com | M46: treasurer@ashfordra.co.uk | N46: 8R980226LF605935P | O46: Sue Goddard, 27 Doris Road, Ashford, TW15 1LS, United Kingdom | P46: Confirmed | Q46: Ashford Residents Association Membership | S46: 0 | U46: 0 | AC46: 1 | AE46: 177.55 | AF46: 27 Doris Road | AH46: Ashford | AJ46: TW15 1LS | AK46: United Kingdom | AL46: 1780000000 | AM46: treasurer@ashfordra.co.uk Household Membership Fee Payment Link Ashford Residents Association (ARA TW15) | AO46: GB | AP46: Credit
B47: 21/03/2026 | C47: 0.59582176 | D47: GMT | E47: barry muggeridge | F47: Membership Fee | G47: Completed | H47: GBP | I47: 5 | J47: -0.45 | K47: 4.55 | L47: barrylandrover@yahoo.com | M47: treasurer@ashfordra.co.uk | N47: 23M94648CC9579843 | O47: barry, muggeridge, 41 Chattern Road, Ashford, Middlesex, TW15 1AE, United Kingdom | P47: Confirmed | Q47: Ashford Residents Association Membership | S47: 0 | U47: 0 | AC47: 1 | AE47: 182.1 | AF47: 41 Chattern Road | AH47: Ashford | AI47: Middlesex | AJ47: TW15 1AE | AK47: United Kingdom | AL47: 1780000000 | AM47: treasurer@ashfordra.co.uk Household Membership Fee Payment Link Ashford Residents Association (ARA TW15) | AO47: GB | AP47: Credit
B48: 21/03/2026 | C48: 0.64695602 | D48: GMT | E48: roisin mackey | F48: Membership Fee | G48: Completed | H48: GBP | I48: 5 | J48: -0.45 | K48: 4.55 | L48: roisin49b@aol.com | M48: treasurer@ashfordra.co.uk | N48: 3VH09413SY900254J | O48: roisin kennedy, 61 Gilmore Crescent, Ashford, Middlesex, TW152DD, United Kingdom | P48: Confirmed | Q48: Ashford Residents Association Membership | S48: 0 | U48: 0 | AC48: 1 | AE48: 186.65 | AF48: 61 Gilmore Crescent | AH48: Ashford | AI48: Middlesex | AJ48: TW152DD | AK48: United Kingdom | AL48: 2080000000 | AM48: treasurer@ashfordra.co.uk Household Membership Fee Payment Link Ashford Residents Association (ARA TW15) | AO48: GB | AP48: Credit
B49: 23/03/2026 | C49: 0.88671296 | D49: GMT | E49: JEANNETTE BROWN | F49: Donation | G49: Completed | H49: GBP | I49: 25 | J49: -0.6 | K49: 24.4 | L49: nettebrown57@gmail.com | M49: treasurer@ashfordra.co.uk | N49: 1FV85835RE1720818 | O49: JEANNETTE, BROWN, 15 DANE ROAD, Ashford, Ashford, MIDDLESEX, TW15 1QJ, United Kingdom | P49: Confirmed | Q49: Ashford Residents Association Donation | S49: 0 | U49: 0 | V49: We would love to say thank you - Please leave your comments and details here. | W49: Jeannette Brown. member since Sept 2025. This is a donation. I think for your time spent freely, specific updates you send us, £5 m'ship is too low. I think£12=£1 pm is affordable to most. Thank yo | AC49: 1 | AD49: 4.86e+15 | AE49: 211.05 | AF49: 15 DANE ROAD, Ashford | AH49: Ashford | AI49: MIDDLESEX | AJ49: TW15 1QJ | AK49: United Kingdom | AM49: treasurer@ashfordra.co.uk Donations Payment Link Ashford Residents Association (ARA TW15) | AO49: GB | AP49: Credit
B50: 28/03/2026 | C50: 0.72054398 | D50: GMT | F50: Transfer to MetroBank | G50: Completed | H50: GBP | I50: -10 | J50: 0 | K50: -10 | L50: treasurer@ashfordra.co.uk | N50: 90G34723YR350341U | U50: 0 | AE50: 201.05 | AP50: Debit
B51: 30/03/2026 | C51: 0.71615741 | D51: BST | F51: Transfer to MetroBank | G51: Completed | H51: GBP | I51: -201.05 | J51: 0 | K51: -201.05 | L51: treasurer@ashfordra.co.uk | N51: 36415573KW767124Y | U51: 0 | AE51: 0 | AP51: Debit
I59: Gross | J59: Fees | K59: Total
G60: Membership Fees | I60: =SUMIF(F:F,"Membership Fee",I:I) -> 195 | J60: =SUMIF(F:F,"Membership Fee",J:J) -> -17.93 | K60: =SUMIF(F:F,"Membership Fee",K:K) -> 177.07
G61: Donations | I61: =SUMIF(F:F,"Donation",I:I) -> 35 | J61: =SUMIF(F:F,"Donation",J:J) -> -1.02 | K61: =SUMIF(F:F,"Donation",K:K) -> 33.98
G62: Transfer to Bank | I62: =SUMIF(F:F,"Transfer to MetroBank",I:I) -> -211.05 | J62: =SUMIF(F:F,"Transfer to MetroBank",J:J) -> 0 | K62: =SUMIF(F:F,"Transfer to MetroBank",K:K) -> -211.05
G63: Total | I63: =SUM(I60:I62) -> 18.95 | J63: =SUM(J60:J62) -> -18.95 | K63: =SUM(K60:K62) -> 0

Sheet ALL MEMBERS
A1: Members No | B1: Date Registered | C1: Full Name | D1: First Name | E1: Surname | F1: Road Name | G1: Postcode | H1: Email | I1: Primary Email | J1: Sent Welcome | K1: Member Source | L1: 25/26 Membership Date Paid | M1: 26/27 Membership Date Paid | N1: Membership Fee | O1: Donation | P1: Payment Type | Q1: Members No | R1: Notes | S1: Renewal Date | T1: Session | U1: Status
A2: =Q2 -> 1 | B2: 45710 | C2: =CONCATENATE(D:D," ",E:E) -> John Dickens | D2: John | E2: Dickens | F2: Chesterfield Road | G2: TW15 2ND | H2: jcdickens@talktalk.net | I2: jcdickens@talktalk.net | J2: Yes | K2: Committee | L2: 45776 | M2: 27/3/26 | N2: 5 | P2: Bank Transfer | Q2: 1 | R2: Committee Chairman | S2: 46391 | T2: Committee | U2: Active
A3: =Q3 -> 2 | B3: 45710 | C3: =CONCATENATE(D:D," ",E:E) -> Penny Kielty | D3: Penny | E3: Kielty | F3: Brownrigg Road | G3: TW15 2TL | H3: penny.kielty@hotmail.co.uk | I3: penny.kielty@hotmail.co.uk | J3: Yes | K3: Committee | L3: 45776 | M3: 21/3/26 | N3: 5 | P3: Offset Exp | Q3: 2 | R3: Committee Secretary | S3: 46478 | T3: Committee | U3: Active
A4: =Q4 -> 3 | B4: 45710 | C4: =CONCATENATE(D:D," ",E:E) -> Julie Holman | D4: Julie | E4: Holman | F4: Rex Avenue | G4: TW15 2DA | H4: julesaholman@gmail.com | I4: julesaholman@gmail.com | J4: Yes | K4: Committee | L4: 45782 | M4: 20/4/2026 | N4: 5 | P4: Bank Transfer | Q4: 3 | R4: Committee Panel | S4: 46392 | T4: Committee | U4: Active
A5: =Q5 -> 4 | B5: 45710 | C5: =CONCATENATE(D:D," ",E:E) -> Andrew Lewis | D5: Andrew | E5: Lewis | F5: Ford Close | G5: TW15 3SB | H5: and_lewis@btinternet.com | I5: and_lewis@btinternet.com | J5: Yes | K5: Sign Up Sheet | L5: 46001 | N5: 5 | Q5: 4 | S5: 46366 | T5: Member | U5: Active
A6: =Q6 -> 5 | B6: 45710 | C6: =CONCATENATE(D:D," ",E:E) -> Anne Crudgington | D6: Anne | E6: Crudgington | F6: Parkland Grove | G6: TW15 2JW | H6: annecrudgington@yahoo.com | I6: annecrudgington@yahoo.com | J6: Yes | K6: Sign Up Sheet | L6: 46015 | N6: 5 | Q6: 5 | R6: Paid by Maureen Crudgington (Metro bank) | S6: 46380 | T6: Member | U6: Active
A7: =Q7 -> 6 | B7: 45710 | C7: =CONCATENATE(D:D," ",E:E) -> Bob Baldry | D7: Bob | E7: Baldry | F7: Parkland Grove | G7: TW15 2JN | H7: bobbaldry@hotmail.com | I7: bobbaldry@hotmail.com | J7: Yes | K7: Sign Up Sheet | L7: 45831 | Q7: 6 | R7: Family membership with SUE BLAND/paid by Sue | S7: 46196 | T7: Member | U7: Active
A8: =Q8 -> 7 | B8: 45710 | C8: =CONCATENATE(D:D," ",E:E) -> Carol Kielty | D8: Carol | E8: Kielty | F8: Exforde Avenue | G8: TW15 2EF | H8: jim.kielty@btinternet.com | I8: jim.kielty@btinternet.com | J8: Yes | K8: Sign Up Sheet | L8: 45776 | M8: 46138 | N8: 5 | P8: Cash | Q8: 7 | R8: Cash to Penny who then paid by Bank Transfer | S8: 46478 | T8: Member | U8: Active
A9: =Q9 -> 8 | B9: 45710 | C9: =CONCATENATE(D:D," ",E:E) -> Carol Wooley | D9: Carol | E9: Wooley | F9: Dorset Road | G9: TW15 3BY | H9: k.e.woolley@btinternet.com | I9: k.e.woolley@btinternet.com | J9: Yes | K9: Sign Up Sheet | Q9: 8 | T9: Member | U9: Active
A10: =Q10 -> 9 | B10: 45710 | C10: =CONCATENATE(D:D," ",E:E) -> Carole Baxter | D10: Carole | E10: Baxter | F10: Manor Road | G10: TW15 2SL | H10: cdandab23@gmail.com | I10: cdandab23@gmail.com | J10: Yes | K10: Sign Up Sheet | L10: 45825 | N10: 5 | Q10: 9 | S10: 46190 | T10: Member | U10: Active
A11: =Q11 -> 10 | B11: 45710 | C11: =CONCATENATE(D:D," ",E:E) -> Caroline Shannon | D11: Caroline | E11: Shannon | F11: Chesterfield Road | G11: TW15 2ND | H11: shannon.caroline@btinternet.com | I11: shannon.caroline@btinternet.com | J11: Yes | K11: Sign Up Sheet | L11: 46002 | N11: 5 | Q11: 10 | S11: 46367 | T11: Member | U11: Leaver
A12: =Q12 -> 11 | B12: 45710 | C12: =CONCATENATE(D:D," ",E:E) -> Christine Lloyd | D12: Christine | E12: Lloyd | F12: Gordon Road | G12: TW15 3ES | H12: c.lloyd01@btinternet.com | I12: c.lloyd01@btinternet.com | J12: Yes | K12: Sign Up Sheet | L12: 46027 | Q12: 11 | S12: 46392 | T12: Member | U12: Active
A13: =Q13 -> 12 | B13: 45710 | C13: =CONCATENATE(D:D," ",E:E) -> Christine Wooster | D13: Christine | E13: Wooster | F13: Percy Avenue | G13: TW15 2PB | H13: chris.wooster@btinternet.com | I13: chris.wooster@btinternet.com | J13: Yes | K13: Sign Up Sheet | L13: 45826 | N13: 10 | Q13: 12 | R13: Paid again 10/12/25 - hold for 2026 fee | S13: 46191 | T13: Member | U13: Active
A14: =Q14 -> 13 | B14: 45710 | C14: =CONCATENATE(D:D," ",E:E) -> David & Tracey Outhwaite | D14: David & Tracey | E14: Outhwaite | G14: TW15 3JH | H14: davidouthwaite@hotmail.com | I14: davidouthwaite@hotmail.com | J14: Yes | K14: Sign Up Sheet | Q14: 13 | T14: Member | U14: Active
A15: =Q15 -> 14 | B15: 45710 | C15: =CONCATENATE(D:D," ",E:E) -> David Lee | D15: David | E15: Lee | F15: Gordon Road | G15: TW15 3EU | H15: madlee01@yahoo.co.uk | I15: madlee01@yahoo.co.uk | J15: Yes | K15: Sign Up Sheet | L15: 45985 | N15: 5 | Q15: 14 | S15: 46350 | T15: Member | U15: Active
A16: =Q16 -> 15 | B16: 45710 | C16: =CONCATENATE(D:D," ",E:E) -> David Small | D16: David | E16: Small | F16: The Wickets | G16: TW15 2RR | H16: davidjsmall@btinternet.com | I16: davidjsmall@btinternet.com | J16: Yes | K16: Sign Up Sheet | L16: 46007 | N16: 5 | Q16: 15 | S16: 46372 | T16: Member | U16: Active
A17: =Q17 -> 16 | B17: 45710 | C17: =CONCATENATE(D:D," ",E:E) -> Dennis & Joan Leeks | D17: Dennis & Joan | E17: Leeks | F17: Ford Close | G17: TW15 3SB | H17: dandjLeeks@btinternet.com | I17: dandjLeeks@btinternet.com | J17: Yes | K17: Sign Up Sheet | L17: 46001 | Q17: 16 | S17: 46366 | T17: Member | U17: Active
A18: =Q18 -> 17 | B18: 45710 | C18: =CONCATENATE(D:D," ",E:E) -> Frank & Laura Greaves | D18: Frank & Laura | E18: Greaves | G18: TW15 3JU | H18: fandlgreaves@gmail.com | I18: fandlgreaves@gmail.com | J18: Yes | K18: Sign Up Sheet | Q18: 17 | T18: Member | U18: Active
A19: =Q19 -> 18 | B19: 45710 | C19: =CONCATENATE(D:D," ",E:E) -> Geoffrey Rippingale | D19: Geoffrey | E19: Rippingale | G19: TW15 2SN | H19: gripp@btinternet.com | I19: gripp@btinternet.com | J19: Yes | K19: Sign Up Sheet | Q19: 18 | T19: Member | U19: Active
A20: =Q20 -> 19 | B20: 45710 | C20: =CONCATENATE(D:D," ",E:E) -> Greg Neall | D20: Greg | E20: Neall | F20: Doris Road | G20: TW15 1LR | H20: greg@wakeupyourwealth.com | I20: greg@wakeupyourwealth.com | J20: Yes | K20: Sign Up Sheet | L20: 45991 | Q20: 19 | R20: Councillor - no payment required | S20: 46356 | T20: Member | U20: Active
A21: =Q21 -> 20 | B21: 45710 | C21: =CONCATENATE(D:D," ",E:E) -> Helen Collis | D21: Helen | E21: Collis | F21: Chaucer Road | G21: TW15 2QX | H21: collid2@virginmedia.com | I21: collid2@virginmedia.com | J21: Yes | K21: Sign Up Sheet | L21: 45991 | N21: 5 | Q21: 20 | S21: 46356 | T21: Member | U21: Active
A22: =Q22 -> 21 | B22: 45710 | C22: =CONCATENATE(D:D," ",E:E) -> Helen Mason | D22: Helen | E22: Mason | G22: TW15 2HF | H22: helenlmason@hotmail.co.uk | I22: helenlmason@hotmail.co.uk | J22: Yes | K22: Sign Up Sheet | Q22: 21 | T22: Member | U22: Active
A23: =Q23 -> 22 | B23: 45710 | C23: =CONCATENATE(D:D," ",E:E) -> Jean & Ian Parry | D23: Jean & Ian | E23: Parry | F23: Gilmore Crescent | G23: TW15 2DE | H23: jicparry@aol.com | I23: jicparry@aol.com | J23: Yes | K23: Sign Up Sheet | L23: 45927 | Q23: 22 | S23: 46292 | T23: Member | U23: Active
A24: =Q24 -> 23 | B24: 45710 | C24: =CONCATENATE(D:D," ",E:E) -> Jackie & Les Brown | D24: Jackie & Les | E24: Brown | G24: TW15 3BX | H24: lesandjackiebrown@hotmail.co.uk | I24: lesandjackiebrown@hotmail.co.uk | J24: Yes | K24: Sign Up Sheet | M24: 25/4/26 | N24: 5 | P24: Cash | Q24: 23 | S24: 46391 | T24: Member | U24: Active
A25: =Q25 -> 24 | B25: 45710 | C25: =CONCATENATE(D:D," ",E:E) -> Jane Dobbie | D25: Jane | E25: Dobbie | G25: TW15 255 | H25: jane@padcroft.org | I25: jane@padcroft.org | J25: Yes | K25: Sign Up Sheet | Q25: 24 | T25: Member | U25: Active
A26: =Q26 -> 25 | B26: 45710 | C26: =CONCATENATE(D:D," ",E:E) -> Jenny Upton | D26: Jenny | E26: Upton | F26: Gordon Road | G26: TW15 3EU | H26: daveupton@btopenworld.com | I26: daveupton@btopenworld.com | J26: Yes | K26: Sign Up Sheet | L26: 46015 | N26: 5 | Q26: 25 | S26: 46380 | T26: Member | U26: Active
A27: =Q27 -> 26 | B27: 45710 | C27: =CONCATENATE(D:D," ",E:E) -> John & Angela Burns | D27: John & Angela | E27: Burns | F27: Reedsfield Road | G27: TW15 2HE | H27: jfburns14@hotmail.com | I27: jfburns14@hotmail.com | J27: Yes | K27: Sign Up Sheet | L27: 45994 | Q27: 26 | S27: 46359 | T27: Member | U27: Active
A28: =Q28 -> 27 | B28: 45710 | C28: =CONCATENATE(D:D," ",E:E) -> John Ibbett | D28: John | E28: Ibbett | F28: Clifford Grove | G28: TW15 2JT | H28: john@ibbett.me.uk | I28: john@ibbett.me.uk | J28: Yes | K28: Sign Up Sheet | Q28: 27 | T28: Member | U28: Active
A29: =Q29 -> 28 | B29: 45710 | C29: =CONCATENATE(D:D," ",E:E) -> John Purser | D29: John | E29: Purser | F29: Woodthorpe Road | G29: TW15 2RU | H29: jkpurser@yahoo.com | I29: jkpurser@yahoo.com | J29: Yes | K29: Sign Up Sheet | L29: 45891 | Q29: 28 | R29: Paid by Megan Purser, same household | S29: 46256 | T29: Member | U29: Active
A30: =Q30 -> 29 | B30: 45710 | C30: =CONCATENATE(D:D," ",E:E) -> Linda Bannister | D30: Linda | E30: Bannister | F30: Chestnut Road | G30: TW15 1DD | H30: l.bannister954@btinternet.com | I30: l.bannister954@btinternet.com | J30: Yes | K30: Sign Up Sheet | L30: 46003 | N30: 5 | Q30: 29 | S30: 46368 | T30: Member | U30: Active
A31: =Q31 -> 30 | B31: 45710 | C31: =CONCATENATE(D:D," ",E:E) -> Linda Nicolls | D31: Linda | E31: Nicolls | G31: TW15 2RR | H31: linnicholls@yahoo.co.uk | I31: linnicholls@yahoo.co.uk | J31: Yes | K31: Sign Up Sheet | Q31: 30 | T31: Member | U31: Active
A32: =Q32 -> 31 | B32: 45710 | C32: =CONCATENATE(D:D," ",E:E) -> Lyn Weetch | D32: Lyn | E32: Weetch | F32: Wolsey Road | G32: TW15 2RA | H32: weetch.family@btinternet.com | I32: weetch.family@btinternet.com | J32: Yes | K32: Sign Up Sheet | Q32: 31 | T32: Member | U32: Active
A33: =Q33 -> 32 | B33: 45710 | C33: =CONCATENATE(D:D," ",E:E) -> Marilyn Castle | D33: Marilyn | E33: Castle | G33: TW15 2JY | H33: marilyncastle107@btinternet.com | I33: marilyncastle107@btinternet.com | J33: Yes | K33: Sign Up Sheet | Q33: 32 | T33: Member | U33: Active
A34: =Q34 -> 33 | B34: 45710 | C34: =CONCATENATE(D:D," ",E:E) -> Megan Purser | D34: Megan | E34: Purser | F34: Woodthorpe Road | G34: TW15 2RU | H34: meganpurser@yahoo.com | I34: meganpurser@yahoo.com | J34: Yes | K34: Sign Up Sheet | L34: 45891 | N34: 5 | Q34: 33 | S34: 46256 | T34: Member | U34: Active
A35: =Q35 -> 34 | B35: 45710 | C35: =CONCATENATE(D:D," ",E:E) -> Pam Brazier | D35: Pam | E35: Brazier | G35: TW15 3ET | H35: pambrazier@gmail.com | I35: pambrazier@gmail.com | J35: Yes | K35: Sign Up Sheet | Q35: 34 | T35: Member | U35: Active
A36: =Q36 -> 35 | B36: 45710 | C36: =CONCATENATE(D:D," ",E:E) -> Patricia Kielty | D36: Patricia | E36: Kielty | F36: Brownrigg Road | G36: TW15 2TL | H36: pat.kielty@hotmail.co.uk | I36: pat.kielty@hotmail.co.uk | J36: Yes | K36: Sign Up Sheet | L36: 45776 | M36: 21/3/26 | N36: 0 | Q36: 35 | R36: Family Membership | S36: 46113 | T36: Member | U36: Active
A37: =Q37 -> 36 | B37: 45710 | C37: =CONCATENATE(D:D," ",E:E) -> Patricia Holmes | D37: Patricia | E37: Holmes | F37: Gilmore Crescent | G37: TW15 2DE | H37: anxa@btinternet.com | I37: anxa@btinternet.com | J37: Yes | K37: Sign Up Sheet | L37: 45831 | N37: 5 | Q37: 36 | S37: 46196 | T37: Member | U37: Active
A38: =Q38 -> 37 | B38: 45710 | C38: =CONCATENATE(D:D," ",E:E) -> Peter Davies | D38: Peter | E38: Davies | F38: Brownrigg Road | G38: TW15 2TL | H38: pcdavies54@hotmail.com | I38: pcdavies54@hotmail.com | J38: Yes | K38: Sign Up Sheet | L38: 46029 | Q38: 37 | R38: Already paid £5 to Last ARA | S38: 46394 | T38: Member | U38: Active
A39: =Q39 -> 38 | B39: 45710 | C39: =CONCATENATE(D:D," ",E:E) -> Phil Henley | D39: Phil | E39: Henley | F39: Village Way | G39: TW15 2LB | H39: peehen@talk21.com | I39: peehen@talk21.com | J39: Yes | K39: Sign Up Sheet | L39: 46003 | N39: 5 | Q39: 38 | S39: 46368 | T39: Member | U39: Active
A40: =Q40 -> 39 | B40: 45710 | C40: =CONCATENATE(D:D," ",E:E) -> Philomena Meddelton | D40: Philomena | E40: Meddelton | F40: Village Way | G40: TW15 2JU | H40: pmeddelton@gmail.com | I40: pmeddelton@gmail.com | J40: Yes | K40: Committee | L40: 45847 | N40: 5 | Q40: 39 | R40: Committee Panel | S40: 46212 | T40: Committee | U40: Active
A41: =Q41 -> 40 | B41: 45710 | C41: =CONCATENATE(D:D," ",E:E) -> Richard Ancill | D41: Richard | E41: Ancill | F41: Parkland Grove | G41: TW15 2JP | H41: r2rsa@btinternet.com | I41: r2rsa@btinternet.com | J41: Yes | K41: Sign Up Sheet | L41: 45840 | N41: 5 | Q41: 40 | S41: 46205 | T41: Member | U41: Active
A42: =Q42 -> 41 | B42: 45710 | C42: =CONCATENATE(D:D," ",E:E) -> Richard Kim | D42: Richard | E42: Kim | G42: TW15 3JR | H42: richardk2707@gmail.com | I42: richardk2707@gmail.com | J42: Yes | K42: Sign Up Sheet | Q42: 41 | T42: Member | U42: Active
A43: =Q43 -> 42 | B43: 45710 | C43: =CONCATENATE(D:D," ",E:E) -> Sheila O'Donovan | D43: Sheila | E43: O'Donovan | F43: Parkland Grove | G43: TW15 2JN | H43: sm_odonovan@btinternet.com | I43: sm_odonovan@btinternet.com | J43: Yes | K43: Sign Up Sheet | L43: 45987 | Q43: 42 | S43: 46352 | T43: Member | U43: Active
A44: =Q44 -> 43 | B44: 45710 | C44: =CONCATENATE(D:D," ",E:E) -> Steve Wherlock | D44: Steve | E44: Wherlock | F44: Portland Road | G44: TW15 3BT | H44: swherlock@live.co.uk | I44: swherlock@live.co.uk | J44: Yes | K44: Sign Up Sheet | L44: 45987 | N44: 5 | O44: 15 | Q44: 43 | R44: Paid by Bank Transfer | S44: 46352 | T44: Member | U44: Active
A45: =Q45 -> 44 | B45: 45710 | C45: =CONCATENATE(D:D," ",E:E) -> Stuart Webster | D45: Stuart | E45: Webster | F45: Parkland Grove | G45: TW15 2JB | H45: stuartwebster50@gmail.com | I45: stuartwebster50@gmail.com | J45: Yes | K45: Sign Up Sheet | Q45: 44 | T45: Member | U45: Active
A46: =Q46 -> 45 | B46: 45710 | C46: =CONCATENATE(D:D," ",E:E) -> Susan Bland | D46: Susan | E46: Bland | F46: Parkland Grove | G46: TW15 2JN | H46: sbland_@hotmail.com | I46: sbland_@hotmail.com | J46: Yes | K46: Sign Up Sheet | L46: 45831 | N46: 5 | Q46: 45 | S46: 46196 | T46: Member | U46: Active
A47: =Q47 -> 46 | B47: 45710 | C47: =CONCATENATE(D:D," ",E:E) -> Sue Claxton | D47: Sue | E47: Claxton | G47: TW15 3JH | H47: susanmclaxton@gmail.com | I47: susanmclaxton@gmail.com | J47: Yes | K47: Sign Up Sheet | Q47: 46 | T47: Member | U47: Active
A48: =Q48 -> 47 | B48: 45710 | C48: =CONCATENATE(D:D," ",E:E) -> Valerie Scott | D48: Valerie | E48: Scott | F48: Chaucer Road | G48: TW15 2QU | H48: val.scott2@btinternet.com | I48: val.scott2@btinternet.com | J48: Yes | K48: Sign Up Sheet | L48: 46010 | N48: 5 | Q48: 47 | S48: 46375 | T48: Member | U48: Active
A49: =Q49 -> 48 | B49: 45722 | C49: =CONCATENATE(D:D," ",E:E) -> Russell Nicol | D49: Russell | E49: Nicol | H49: russ.nicol@blueyonder.co.uk | I49: russ.nicol@blueyonder.co.uk | J49: Yes | K49: Email | Q49: 48 | T49: Member | U49: Active
A50: =Q50 -> 49 | B50: 45723 | C50: =CONCATENATE(D:D," ",E:E) -> Susan Johnson | D50: Susan | E50: Johnson | H50: sueandbrianjohnson@yahoo.co.uk | I50: sueandbrianjohnson@yahoo.co.uk | J50: Yes | K50: Email | L50: 45780 | M50: 46128 | N50: 5 | P50: Bank Transfer | Q50: 49 | S50: 46392 | T50: Member | U50: Active
A51: =Q51 -> 50 | B51: 45727 | C51: =CONCATENATE(D:D," ",E:E) -> Sally George | D51: Sally | E51: George | F51: Kingston Cresent | G51: TW15 3NE | H51: sallygeorge@hotmail.co.uk | I51: sallygeorge@hotmail.co.uk | J51: Yes | K51: Sign Up Sheet | L51: 46003 | N51: 5 | Q51: 50 | S51: 46368 | T51: Member | U51: Active
A52: =Q52 -> 51 | B52: 45744 | C52: =CONCATENATE(D:D," ",E:E) -> Gareth Williams | D52: Gareth | E52: Williams | H52: gareth.jon.williams@gmail.com | I52: gareth.jon.williams@gmail.com | J52: Yes | K52: Neighbourhood Watch | Q52: 51 | T52: Member | U52: Active
A53: =Q53 -> 52 | B53: 45744 | C53: =CONCATENATE(D:D," ",E:E) -> Gordon Briggs | D53: Gordon | E53: Briggs | F53: Salcome Road | G53: TW15 3BS | H53: gordon.briggs@hotmail.co.uk | I53: gordon.briggs@hotmail.co.uk | J53: Yes | K53: Sign Up Sheet | L53: 46001 | N53: 5 | Q53: 52 | S53: 46366 | T53: Member | U53: Active
A54: =Q54 -> 53 | B54: 45744 | C54: =CONCATENATE(D:D," ",E:E) -> Sally Pawson | D54: Sally | E54: Pawson | F54: Ashgrove Road | G54: TW15 1NU | H54: sjpawson@gmail.com | I54: sjpawson@gmail.com | J54: Yes | K54: Nextdoor | L54: 45777 | N54: 5 | Q54: 53 | S54: 46142 | T54: Member | U54: Active
A55: =Q55 -> 54 | B55: 45747 | C55: =CONCATENATE(D:D," ",E:E) -> Nik Urquhart | D55: Nik | E55: Urquhart | F55: Church Road | G55: TW15 2UY | H55: nikurquhart@yahoo.co.uk | I55: nikurquhart@yahoo.co.uk | J55: Yes | K55: Committee | L55: 45791 | N55: 5 | Q55: 54 | R55: Committee Panel | S55: 46156 | T55: Committee | U55: Active
A56: =Q56 -> 55 | B56: 45753 | C56: =CONCATENATE(D:D," ",E:E) -> Valerie Wrightson | D56: Valerie | E56: Wrightson | H56: vjwri43@yahoo.com | I56: vjwri43@yahoo.com | J56: Yes | K56: Email | Q56: 55 | T56: Member | U56: Active
A57: =Q57 -> 56 | B57: 45763 | C57: =CONCATENATE(D:D," ",E:E) -> John Swaffield | D57: John | E57: Swaffield | H57: swaffield@btinternet.com | I57: swaffield@btinternet.com | J57: Yes | K57: Email | L57: 45985 | N57: 5 | Q57: 56 | S57: 46350 | T57: Member | U57: Active
A58: =Q58 -> 57 | B58: 45763 | C58: =CONCATENATE(D:D," ",E:E) -> Lyn Blake | D58: Lyn | E58: Blake | F58: Village Way | G58: TW15 2LB | H58: blake539@btinternet.com | I58: blake539@btinternet.com | J58: Yes | K58: Sign Up Sheet | L58: 46028 | N58: 5 | Q58: 57 | S58: 46393 | T58: Member | U58: Active
A59: =Q59 -> 58 | B59: 45763 | C59: =CONCATENATE(D:D," ",E:E) -> Richard Pawson | D59: Richard | E59: Pawson | F59: Ashgrove Road | G59: TW15 1NU | H59: rmpawson@gmail.com | I59: rmpawson@gmail.com | J59: Yes | K59: Email | L59: 45777 | Q59: 58 | R59: Family Membership, paid by Sally Pawson | S59: 46142 | T59: Member | U59: Active
A60: =Q60 -> 59 | B60: 45763 | C60: =CONCATENATE(D:D," ",E:E) -> Stella Walter | D60: Stella | E60: Walter | F60: Meadway | G60: TW15 2TJ | H60: kevinwalter6@hotmail.com | I60: kevinwalter6@hotmail.com | J60: Yes | K60: Email | L60: 46003 | N60: 5 | Q60: 59 | S60: 46368 | T60: Member | U60: Active
A61: =Q61 -> 60 | B61: 45763 | C61: =CONCATENATE(D:D," ",E:E) -> Vatsal Patel | D61: Vatsal | E61: Patel | H61: vatz1996@hotmail.co.uk | I61: vatz1996@hotmail.co.uk | J61: Yes | K61: Email | Q61: 60 | T61: Member | U61: Active
A62: =Q62 -> 61 | B62: 45765 | C62: =CONCATENATE(D:D," ",E:E) -> Irfan Younas | D62: Irfan | E62: Younas | F62: Parkland Grove | G62: TW15 2JR | H62: miyounas@gmail.com | I62: miyounas@gmail.com | J62: Yes | K62: Sign Up Sheet | Q62: 61 | T62: Member | U62: Active
A63: =Q63 -> 62 | B63: 45766 | C63: =CONCATENATE(D:D," ",E:E) -> Carol Pringle | D63: Carol | E63: Pringle | H63: carol.gerald10@yahoo.co.uk | I63: carol.gerald10@yahoo.co.uk | J63: Yes | K63: Email | Q63: 62 | T63: Member | U63: Active
A64: =Q64 -> 63 | B64: 45766 | C64: =CONCATENATE(D:D," ",E:E) -> Caroline Rogerson | D64: Caroline | E64: Rogerson | H64: carogerson57@yahoo.co.uk | I64: carogerson57@yahoo.co.uk | J64: Yes | K64: Nextdoor | Q64: 63 | T64: Member | U64: Active
A65: =Q65 -> 64 | B65: 45766 | C65: =CONCATENATE(D:D," ",E:E) -> Chris Chattam | D65: Chris | E65: Chattam | H65: christine.chattam@gmail.com | I65: christine.chattam@gmail.com | J65: Yes | K65: Nextdoor | Q65: 64 | T65: Member | U65: Active
A66: =Q66 -> 65 | B66: 45766 | C66: =CONCATENATE(D:D," ",E:E) -> Dareen A | D66: Dareen | E66: A | H66: zany247@gmail.com | I66: zany247@gmail.com | J66: Yes | K66: Nextdoor | Q66: 65 | T66: Member | U66: Active
A67: =Q67 -> 66 | B67: 45766 | C67: =CONCATENATE(D:D," ",E:E) -> Debbie Potter | D67: Debbie | E67: Potter | H67: debbierpotter@yahoo.co.uk | I67: debbierpotter@yahoo.co.uk | J67: Yes | K67: Email | Q67: 66 | T67: Member | U67: Active
A68: =Q68 -> 67 | B68: 45766 | C68: =CONCATENATE(D:D," ",E:E) -> Melanie Hughes | D68: Melanie | E68: Hughes | H68: meljane224@yahoo.co.uk | I68: meljane224@yahoo.co.uk | J68: Yes | K68: Email | L68: 45985 | N68: 5 | Q68: 67 | S68: 46350 | T68: Member | U68: Active
A69: =Q69 -> 68 | B69: 45766 | C69: =CONCATENATE(D:D," ",E:E) -> Natasha T | D69: Natasha | E69: T | H69: nlpsub@outlook.com | I69: nlpsub@outlook.com | J69: Yes | K69: Nextdoor | Q69: 68 | T69: Member | U69: Active
A70: =Q70 -> 69 | B70: 45766 | C70: =CONCATENATE(D:D," ",E:E) -> Sue Kielty | D70: Sue | E70: Kielty | F70: Arlington Road | G70: TW15 2LS | H70: suekielty@hotmail.co.uk | I70: suekielty@hotmail.co.uk | J70: Yes | K70: Nextdoor | L70: 45776 | M70: 24/3/26 | N70: 5 | P70: Bank Transfer | Q70: 69 | R70: Family Membership - paid by Sue | S70: 46113 | T70: Member | U70: Active
A71: =Q71 -> 70 | B71: 45769 | C71: =CONCATENATE(D:D," ",E:E) -> Glen Watson | D71: Glen | E71: Watson | H71: glenn.watson@ashfordrevive.org | I71: glenn.watson@ashfordrevive.org | J71: Yes | K71: Email | Q71: 70 | T71: Member | U71: Active
A72: =Q72 -> 71 | B72: 45770 | C72: =CONCATENATE(D:D," ",E:E) -> Jenny Lomas | D72: Jenny | E72: Lomas | F72: Clarendon Road | G72: TW15 2QA | H72: jenny@lomas.uk | I72: jenny@lomas.uk | J72: Yes | K72: Email | L72: 28/12/25 | N72: 10 | Q72: 71 | R72: Committee Panel. Paid £10 to cover 2025 & 2026. Renew on 1/1/27 | S72: 46388 | T72: Member | U72: Active
A73: =Q73 -> 72 | B73: 45771 | C73: =CONCATENATE(D:D," ",E:E) -> Isabelle Kielty | D73: Isabelle | E73: Kielty | F73: Arlington Road | G73: TW15 2LS | H73: i.kielts2006@gmail.com | I73: i.kielts2006@gmail.com | J73: Yes | K73: Friends & Family | L73: 45776 | M73: 24/3/26 | N73: 0 | Q73: 72 | R73: Family Membership - paid by Sue | S73: 46113 | T73: Member | U73: Active
A74: =Q74 -> 73 | B74: 45771 | C74: =CONCATENATE(D:D," ",E:E) -> Jamieson Kielty | D74: Jamieson | E74: Kielty | F74: Brownrigg Road | G74: TW15 2TL | H74: jamieson.kielty@hotmail.co.uk | I74: jamieson.kielty@hotmail.co.uk | J74: Yes | K74: Friends & Family | L74: 45776 | M74: 21/3/26 | N74: 0 | Q74: 73 | R74: Family Membership | S74: 46113 | T74: Member | U74: Active
A75: =Q75 -> 74 | B75: 45771 | C75: =CONCATENATE(D:D," ",E:E) -> Mark Kielty | D75: Mark | E75: Kielty | F75: Arlington Road | G75: TW15 2LS | H75: mjkielty@hotmail.com | I75: mjkielty@hotmail.com | J75: Yes | K75: Friends & Family | L75: 45776 | M75: 24/3/26 | N75: 5 | Q75: 74 | R75: Family Membership - paid by Sue | S75: 46113 | T75: Member | U75: Active
A76: =Q76 -> 75 | B76: 45771 | C76: =CONCATENATE(D:D," ",E:E) -> John Kielty | D76: John | E76: Kielty | F76: Fontmell Park | G76: TW15 2NW | H76: kilts@btinternet.com | I76: kilts@btinternet.com | J76: Yes | K76: Friends & Family | L76: 45776 | M76: 46138 | N76: 5 | P76: Cash | Q76: 75 | S76: 46478 | T76: Member | U76: Active
A77: =Q77 -> 76 | B77: 45771 | C77: =CONCATENATE(D:D," ",E:E) -> Paul Benson | D77: Paul | E77: Benson | H77: Paulbenson15@hotmail.com | I77: Paulbenson15@hotmail.com | J77: Yes | K77: Nextdoor | Q77: 76 | T77: Member | U77: Active
A78: =Q78 -> 77 | B78: 45776 | C78: =CONCATENATE(D:D," ",E:E) -> Agnieszka Lipka | D78: Agnieszka | E78: Lipka | H78: agnieszka.lipka1212@gmail.com | I78: agnieszka.lipka1212@gmail.com | J78: Yes | K78: Email | Q78: 77 | T78: Member | U78: Active
A79: =Q79 -> 78 | B79: 45776 | C79: =CONCATENATE(D:D," ",E:E) -> Andy Telasai Anak Indit | D79: Andy | E79: Telasai Anak Indit | F79: Ashgrove Road | G79: TW15 1PD | H79: andytelasai@yahoo.com | I79: andytelasai@yahoo.com | J79: Yes | K79: Email | L79: 46000 | N79: 5 | Q79: 78 | S79: 46365 | T79: Member | U79: Active
A80: =Q80 -> 79 | B80: 45776 | C80: =CONCATENATE(D:D," ",E:E) -> Jane Smith | D80: Jane | E80: Smith | H80: smith-j90@sky.com | I80: smith-j90@sky.com | J80: Yes | K80: Sign Up Sheet | L80: 46006 | N80: 5 | Q80: 79 | S80: 46371 | T80: Member | U80: Active
A81: =Q81 -> 80 | B81: 45776 | C81: =CONCATENATE(D:D," ",E:E) -> John Bone | D81: John | E81: Bone | H81: John1301b@gmail.com | I81: John1301b@gmail.com | J81: Yes | K81: Sign Up Sheet | Q81: 80 | T81: Member | U81: Active
A82: =Q82 -> 81 | B82: 45776 | C82: =CONCATENATE(D:D," ",E:E) -> John Wasley | D82: John | E82: Wasley | F82: Chesterfield Road | G82: TW15 2ND | H82: jwasley408@googlemail.com | I82: jwasley408@googlemail.com | J82: Yes | K82: Sign Up Sheet | L82: 46003 | N82: 5 | Q82: 81 | S82: 46368 | T82: Member | U82: Active
A83: =Q83 -> 82 | B83: 45777 | C83: =CONCATENATE(D:D," ",E:E) -> Amanda Mills | D83: Amanda | E83: Mills | H83: millsamanda@live.co.uk | I83: millsamanda@live.co.uk | J83: Yes | K83: Sign Up Sheet | Q83: 82 | T83: Member | U83: Active
A84: =Q84 -> 83 | B84: 45777 | C84: =CONCATENATE(D:D," ",E:E) -> Barry Muggeridge | D84: Barry | E84: Muggeridge | F84: Chattern Road | G84: TW15 1AE | H84: barrylandrover@yahoo.com | I84: barrylandrover@yahoo.com | J84: Yes | K84: Sign Up Sheet | L84: 45777 | M84: 21/3/26 | N84: 5 | Q84: 83 | S84: 46391 | T84: Member | U84: Active
A85: =Q85 -> 84 | B85: 45777 | C85: =CONCATENATE(D:D," ",E:E) -> Heather McIntyre | D85: Heather | E85: McIntyre | F85: Mornington Road | G85: TW15 1NW | H85: heathermcintyre28@btinternet.com | I85: heathermcintyre28@btinternet.com | J85: Yes | K85: Sign Up Sheet | Q85: 84 | T85: Member | U85: Active
A86: =Q86 -> 85 | B86: 45777 | C86: =CONCATENATE(D:D," ",E:E) -> Neeraj Wadhwa | D86: Neeraj | E86: Wadhwa | H86: wadhwaneeraj20@gmail.com | I86: wadhwaneeraj20@gmail.com | J86: Yes | K86: Sign Up Sheet | L86: 46001 | N86: 5 | Q86: 85 | S86: 46366 | T86: Member | U86: Active
A87: =Q87 -> 86 | B87: 45777 | C87: =CONCATENATE(D:D," ",E:E) -> Róisín Kennedy | D87: Róisín | E87: Kennedy | F87: Gilmore Avenue | G87: TW15 2DD | H87: roisin49b@aol.com | I87: roisin49b@aol.com | J87: Yes | K87: Neighbourhood Watch | L87: 45777 | M87: 21/3/26 | N87: 5 | Q87: 86 | R87: Roisin Mackey/Kennedy | S87: 46391 | T87: Member | U87: Active
A88: =Q88 -> 87 | B88: 45777 | C88: =CONCATENATE(D:D," ",E:E) -> Susan Goddard | D88: Susan | E88: Goddard | H88: sue.goddard14@outlook.com | I88: sue.goddard14@outlook.com | J88: Yes | K88: Sign Up Sheet | L88: 45777 | M88: 23/3/26 | N88: 5 | Q88: 87 | S88: 46391 | T88: Member | U88: Active
A89: =Q89 -> 88 | B89: 45778 | C89: =CONCATENATE(D:D," ",E:E) -> Anna Barker | D89: Anna | E89: Barker | H89: annabarker@outlook.com | I89: annabarker@outlook.com | J89: Yes | K89: Sign Up Sheet | Q89: 88 | T89: Member | U89: Active
A90: =Q90 -> 89 | B90: 45778 | C90: =CONCATENATE(D:D," ",E:E) -> Jesus Garcia-Robaina | D90: Jesus | E90: Garcia-Robaina | H90: Jesus.garob@yahoo.co.uk | I90: Jesus.garob@yahoo.co.uk | J90: Yes | K90: Sign Up Sheet | Q90: 89 | T90: Member | U90: Active
A91: =Q91 -> 90 | B91: 45778 | C91: =CONCATENATE(D:D," ",E:E) -> Deb Cousens | D91: Deb | E91: Cousens | F91: Chesterfield Road | G91: TW15 2ND | H91: debbie.cousens.dc@gmail.com | I91: debbie.cousens.dc@gmail.com | J91: Yes | K91: Committee | L91: 45776 | M91: 27/3/26 | N91: 0 | Q91: 90 | R91: Committee Treasurer/Family Membership (John Dickens) | S91: 46391 | T91: Committee | U91: Active
A92: =Q92 -> 91 | B92: 45778 | C92: =CONCATENATE(D:D," ",E:E) -> Kirstie Lucas | D92: Kirstie | E92: Lucas | H92: Kirstie.l@sky.com | I92: Kirstie.l@sky.com | J92: Yes | K92: Sign Up Sheet | Q92: 91 | T92: Member | U92: Active
A93: =Q93 -> 92 | B93: 45778 | C93: =CONCATENATE(D:D," ",E:E) -> Michael Ashdown | D93: Michael | E93: Ashdown | H93: mjashdown@hotmail.com | I93: mjashdown@hotmail.com | J93: Yes | K93: Sign Up Sheet | L93: 45780 | N93: 5 | Q93: 92 | S93: 46145 | T93: Member | U93: Active
A94: =Q94 -> 93 | B94: 45778 | C94: =CONCATENATE(D:D," ",E:E) -> Nabila Ritchie | D94: Nabila | E94: Ritchie | H94: nabila_ritchie@hotmail.com | I94: nabila_ritchie@hotmail.com | J94: Yes | K94: Neighbourhood Watch | L94: 45985 | N94: 5 | Q94: 93 | S94: 46350 | T94: Member | U94: Active
A95: =Q95 -> 94 | B95: 45778 | C95: =CONCATENATE(D:D," ",E:E) -> Pamela Hancock | D95: Pamela | E95: Hancock | H95: pamela_c_hancock@yahoo.co.uk | I95: pamela_c_hancock@yahoo.co.uk | J95: Yes | K95: Neighbourhood Watch | L95: 45859 | N95: 5 | Q95: 94 | S95: 46224 | T95: Member | U95: Active
A96: =Q96 -> 95 | B96: 45778 | C96: =CONCATENATE(D:D," ",E:E) -> Simon Robins | D96: Simon | E96: Robins | F96: Greshem Road | G96: TW15 2BZ | H96: simonrobins1974@gmail.com | I96: simonrobins1974@gmail.com | J96: Yes | K96: Sign Up Sheet | Q96: 95 | T96: Member | U96: Active
A97: =Q97 -> 96 | B97: 45778 | C97: =CONCATENATE(D:D," ",E:E) -> Tessa Whitehorn | D97: Tessa | E97: Whitehorn | H97: tessaclare182@googlemail.com | I97: tessaclare182@googlemail.com | J97: Yes | K97: Neighbourhood Watch | Q97: 96 | T97: Member | U97: Active
A98: =Q98 -> 97 | B98: 45779 | C98: =CONCATENATE(D:D," ",E:E) -> Natalie Rendell | D98: Natalie | E98: Rendell | H98: Therendells@outlook.com | I98: Therendells@outlook.com | J98: Yes | K98: Website | M98: 23/4/2026 | N98: 5 | P98: PayPal | Q98: 97 | S98: 46391 | T98: Member | U98: Active
A99: =Q99 -> 98 | B99: 45779 | C99: =CONCATENATE(D:D," ",E:E) -> Natalie Roberts | D99: Natalie | E99: Roberts | H99: nataliea_roberts@yahoo.co.uk | I99: nataliea_roberts@yahoo.co.uk | J99: Yes | K99: PayPal | L99: 45779 | N99: 5 | Q99: 98 | S99: 46144 | T99: Member | U99: Active
A100: =Q100 -> 99 | B100: 45779 | C100: =CONCATENATE(D:D," ",E:E) -> Vrishikaben Patel | D100: Vrishikaben | E100: Patel | H100: patelvrishika9@gmail.com | I100: patelvrishika9@gmail.com | J100: Yes | K100: Nextdoor | Q100: 99 | T100: Member | U100: Active
...

Sheet <PayPal
A1: Membership Number | B1: Date | C1: Time | D1: Time zone | E1: Name | F1: Type | G1: Status | H1: Currency | I1: Gross | J1: Fees | K1: Net
A2: =_xlfn.XLOOKUP(E2,'ALL MEMBERS x1'!C:C,'ALL MEMBERS x1'!Q:Q) -> 2 | B2: 45776 | C2: 0.79524306 | D2: BST | E2: Penny Kielty | F2: Membership Fee | G2: Completed | H2: GBP | I2: 5 | J2: -0.45 | K2: 4.55
A3: =_xlfn.XLOOKUP(E3,'ALL MEMBERS x1'!C:C,'ALL MEMBERS x1'!Q:Q) -> 74 | B3: 45776 | C3: 0.81466435 | D3: BST | E3: Mark Kielty | F3: Membership Fee | G3: Completed | H3: GBP | I3: 5 | J3: -0.45 | K3: 4.55
A4: =_xlfn.XLOOKUP(E4,'ALL MEMBERS x1'!C:C,'ALL MEMBERS x1'!Q:Q) -> 1 | B4: 45776 | C4: 0.86083333 | D4: BST | E4: John Dickens | F4: Membership Fee | G4: Completed | H4: GBP | I4: 5 | J4: -0.45 | K4: 4.55
A5: =_xlfn.XLOOKUP(E5,'ALL MEMBERS x1'!C:C,'ALL MEMBERS x1'!Q:Q) -> 87 | B5: 45777 | C5: 0.29740741 | D5: BST | E5: Susan Goddard | F5: Membership Fee | G5: Completed | H5: GBP | I5: 5 | J5: -0.45 | K5: 4.55
A6: =_xlfn.XLOOKUP(E6,'ALL MEMBERS x1'!C:C,'ALL MEMBERS x1'!Q:Q) -> 86 | B6: 45777 | C6: 0.43118056 | D6: BST | E6: Róisín Kennedy | F6: Membership Fee | G6: Completed | H6: GBP | I6: 5 | J6: -0.45 | K6: 4.55
A7: =_xlfn.XLOOKUP(E7,'ALL MEMBERS x1'!C:C,'ALL MEMBERS x1'!Q:Q) -> 53 | B7: 45777 | C7: 0.60240741 | D7: BST | E7: Sally Pawson | F7: Membership Fee | G7: Completed | H7: GBP | I7: 5 | J7: -0.45 | K7: 4.55
A8: =_xlfn.XLOOKUP(E8,'ALL MEMBERS x1'!C:C,'ALL MEMBERS x1'!Q:Q) -> 83 | B8: 45777 | C8: 0.62630787 | D8: BST | E8: Barry Muggeridge | F8: Membership Fee | G8: Completed | H8: GBP | I8: 5 | J8: -0.45 | K8: 4.55
A9: =_xlfn.XLOOKUP(E9,'ALL MEMBERS x1'!C:C,'ALL MEMBERS x1'!Q:Q) -> 98 | B9: 45779 | C9: 0.51387731 | D9: BST | E9: Natalie Roberts | F9: Membership Fee | G9: Completed | H9: GBP | I9: 5 | J9: -0.45 | K9: 4.55
A10: =_xlfn.XLOOKUP(E10,'ALL MEMBERS x1'!C:C,'ALL MEMBERS x1'!Q:Q) -> 49 | B10: 45780 | C10: 0.31450231 | D10: BST | E10: Susan Johnson | F10: Membership Fee | G10: Completed | H10: GBP | I10: 5 | J10: -0.45 | K10: 4.55
A11: =_xlfn.XLOOKUP(E11,'ALL MEMBERS x1'!C:C,'ALL MEMBERS x1'!Q:Q) -> 92 | B11: 45780 | C11: 0.39502315 | D11: BST | E11: Michael Ashdown | F11: Membership Fee | G11: Completed | H11: GBP | I11: 5 | J11: -0.45 | K11: 4.55
A12: =_xlfn.XLOOKUP(E12,'ALL MEMBERS x1'!C:C,'ALL MEMBERS x1'!Q:Q) -> 3 | B12: 45782 | C12: 0.54189815 | D12: BST | E12: Julie Holman | F12: Membership Fee | G12: Completed | H12: GBP | I12: 5 | J12: -0.45 | K12: 4.55
A13: =_xlfn.XLOOKUP(E13,'ALL MEMBERS x1'!C:C,'ALL MEMBERS x1'!Q:Q) -> 119 | B13: 45782 | C13: 0.69793981 | D13: BST | E13: Jillian Webb | F13: Membership Fee | G13: Completed | H13: GBP | I13: 5 | J13: -0.45 | K13: 4.55
... A50: =_xlfn.XLOOKUP(E50,'ALL MEMBERS x1'!C:C,'ALL MEMBERS x1'!Q:Q) -> 249 | B50: 45939 | C50: 0.47434028 | D50: BST | E50: Charlotte Atkinson | F50: Membership Fee | G50: Completed | H50: GBP | I50: 5 | J50: -0.45 | K50: 4.55
I53: Gross | J53: Fees | K53: Total
G54: Membership Fees | I54: =SUMIF(F:F,"membership fee",I:I) -> 235 | J54: =SUMIF(F:F,"membership fee",J:J) -> -21.15 | K54: =SUMIF(F:F,"membership fee",K:K) -> 213.85
G55: Donations | I55: =SUMIF(F:F,"donation",I:I) -> 30 | J55: =SUMIF(F:F,"donation",J:J) -> -1.48 | K55: =SUMIF(F:F,"donation",K:K) -> 28.52
G56: Total | I56: =I54+I55 -> 265 | J56: =J54+J55 -> -22.63 | K56: =K54+K55 -> 242.37

Sheet BLANK SIGN UP NEW MEMBERS
A1: ASHFORD RESIDENTS ASSOCATION ** NEW MEMBERS ONLY **
A2: First Name | B2: Surname | C2: Road Name | D2: Post Code | E2: Email Address | F2: Paid £5 Membership Fee

Sheet BLANK SIGN UP SHEET 2
A1: ASHFORD RESIDENTS ASSOCATION ** PAID MEMBERS ONLY **
A2: Full Name | B2: Full Name | C2: Full Name | D2: Full Name | E2: Full Name

Sheet ALL MEMBERS x1
B1: Date | C1: Full Name | D1: First Name | E1: Surname | F1: Road Name | G1: Postcode | H1: Email Address | I1: Sent Welcome | J1: Member Sign Up | K1: Membership Date Paid | L1: Membership Fee | M1: Donation | N1: PayPal Charges | O1: Paid Cash | P1: Total | Q1: Members No | R1: Notes
B2: 45776 | C2: =CONCATENATE(D:D," ",E:E) -> Agnieszka Lipka | D2: Agnieszka | E2: Lipka | H2: agnieszka.lipka1212@gmail.com | I2: Y | J2: EMAIL | P2: =L2+M2+N2+O2 -> 0 | Q2: 77
B3: 45813 | C3: =CONCATENATE(D:D," ",E:E) -> Alan Joel | D3: Alan | E3: Joel | H3: alanj123@btinternet.com | I3: Y | J3: Leaflet | K3: 45834 | L3: 5 | N3: -0.45 | P3: =L3+M3+N3+O3 -> 4.55 | Q3: 134
B4: 45931 | C4: =CONCATENATE(D:D," ",E:E) -> Alev Garner | D4: Alev | E4: Garner | F4: Parkland grove | G4: TW15 2JB | H4: alevgarner@gmail.com | I4: Y | J4: Website | P4: =L4+M4+N4+O4 -> 0 | Q4: 236
B5: 45822 | C5: =CONCATENATE(D:D," ",E:E) -> Alison Blundell | D5: Alison | E5: Blundell | F5: Ford Road | G5: TW15 2RD | H5: alisoneblundell@gmail.com | I5: Y | J5: Sign Up Sheet | P5: =L5+M5+N5+O5 -> 0 | Q5: 143
B6: 45777 | C6: =CONCATENATE(D:D," ",E:E) -> Amanda Mills | D6: Amanda | E6: Mills | H6: millsamanda@live.co.uk | I6: Y | J6: Sign Up Sheet | P6: =L6+M6+N6+O6 -> 0 | Q6: 82
B7: 45710 | C7: =CONCATENATE(D:D," ",E:E) -> Andrew Lewis | D7: Andrew | E7: Lewis | G7: TW15 3SB | H7: and_lewis@btinternet.com | I7: Y | J7: Sign Up Sheet | P7: =L7+M7+N7+O7 -> 0 | Q7: 4
B8: 45780 | C8: =CONCATENATE(D:D," ",E:E) -> Andrew Williams | D8: Andrew | E8: Williams | F8: Ashgrove Road | G8: TW15 1NU | H8: andywilliams290@hotmail.com | I8: Y | J8: WEBSITE | K8: 45993 | L8: 5 | N8: -0.45 | P8: =L8+M8+N8+O8 -> 4.55 | Q8: 100
B9: 45814 | C9: =CONCATENATE(D:D," ",E:E) -> Andrew McLuskey | D9: Andrew | E9: McLuskey | F9: Stanley Road | G9: TW15 2LQ | H9: andrewmcluskey@outlook.com | I9: Y | J9: Sign Up Sheet | P9: =L9+M9+N9+O9 -> 0 | Q9: 138
B10: 45935 | C10: =CONCATENATE(D:D," ",E:E) -> Andrew Russell | D10: Andrew | E10: Russell | F10: Ashford Close | G10: TW15 3JU | H10: Andrewjrussell@yahoo.co.uk | I10: Y | J10: NHW | P10: =L10+M10+N10+O10 -> 0 | Q10: 246
B11: 45776 | C11: =CONCATENATE(D:D," ",E:E) -> Andy Telasai | D11: Andy | E11: Telasai | H11: andytelasai@yahoo.com | I11: Y | J11: EMAIL | P11: =L11+M11+N11+O11 -> 0 | Q11: 78
B12: 45927 | C12: =CONCATENATE(D:D," ",E:E) -> Ann Robinson | D12: Ann | E12: Robinson | F12: Ashgrove Roqa | G12: TW15 1PD | H12: annplan2@yahoo.com | I12: Y | J12: Sign Up Sheet | K12: 45985 | L12: 5 | N12: -0.45 | P12: =L12+M12+N12+O12 -> 4.55 | Q12: 200
B13: 45778 | C13: =CONCATENATE(D:D," ",E:E) -> Anna Barker | D13: Anna | E13: Barker | H13: annabarker@outlook.com | I13: Y | J13: Sign Up Sheet | P13: =L13+M13+N13+O13 -> 0 | Q13: 88
B14: 45710 | C14: =CONCATENATE(D:D," ",E:E) -> Anne Crudgington | D14: Anne | E14: Crudgington | G14: TW15 2JW | H14: annecrudgington@yahoo.com | I14: Y | J14: Sign Up Sheet | P14: =L14+M14+N14+O14 -> 0 | Q14: 5
B15: 45907 | C15: =CONCATENATE(D:D," ",E:E) -> Anne-Maria Eusebio | D15: Anne-Maria | E15: Eusebio | F15: Metcalf Road | G15: TW15 1EZ | H15: amaria.eusebio@gmail.com | I15: Y | J15: Sign Up Sheet | P15: =L15+M15+N15+O15 -> 0 | Q15: 186
B16: 45781 | C16: =CONCATENATE(D:D," ",E:E) -> Ashish Kahol | D16: Ashish | E16: Kahol | H16: ashishkahol@yahoo.co.uk | I16: Y | J16: WEBSITE | P16: =L16+M16+N16+O16 -> 0 | Q16: 117
B17: 45927 | C17: =CONCATENATE(D:D," ",E:E) -> Audrey Aylott | D17: Audrey | E17: Aylott | F17: West Close | G17: TW15 3LU | H17: audreyaylott@outlook.com | I17: Y | J17: Sign Up Sheet | P17: =L17+M17+N17+O17 -> 0 | Q17: 201
B18: 45850 | C18: =CONCATENATE(D:D," ",E:E) -> Barbara McLennan | D18: Barbara | E18: McLennan | H18: barbarajmcl@hotmail.com | I18: Y | J18: PayPal | K18: 45850 | L18: 5 | N18: -0.45 | P18: =L18+M18+N18+O18 -> 4.55 | Q18: 179
B19: 45777 | C19: =CONCATENATE(D:D," ",E:E) -> Barry Muggeridge | D19: Barry | E19: Muggeridge | H19: barrylandrover@yahoo.com | I19: Y | J19: Sign Up Sheet | K19: 45777 | L19: 5 | N19: -0.45 | P19: =L19+M19+N19+O19 -> 4.55 | Q19: 83
B20: 45927 | C20: =CONCATENATE(D:D," ",E:E) -> Barry Clarke | D20: Barry | E20: Clarke | F20: Mayfield Close | G20: TW15 2AT | H20: clarkstw15@hotmsail.co.uk | I20: Y | J20: Sign Up Sheet | P20: =L20+M20+N20+O20 -> 0 | Q20: 202
B21: 45927 | C21: =CONCATENATE(D:D," ",E:E) -> Bernadette Williams | D21: Bernadette | E21: Williams | F21: Ashgrove Road | G21: TW15 1NU | H21: andywilliams1290@hotmail.com | I21: Y | J21: Sign Up Sheet | P21: =L21+M21+N21+O21 -> 0 | Q21: 203
B22: 45710 | C22: =CONCATENATE(D:D," ",E:E) -> Bob Baldry | D22: Bob | E22: Baldry | G22: TW15 2JN | H22: bobbaldry@hotmail.com | I22: Y | J22: Sign Up Sheet | P22: =L22+M22+N22+O22 -> 0 | Q22: 6
B23: 45841 | C23: =CONCATENATE(D:D," ",E:E) -> Brenda Duff | D23: Brenda | E23: Duff | F23: Stanwell Road | G23: TW15 3QH | H23: bcduffcole@yahoo.com | I23: Y | J23: Website | P23: =L23+M23+N23+O23 -> 0 | Q23: 178
B24: 45782 | C24: =CONCATENATE(D:D," ",E:E) -> Callum Dyer | D24: Callum | E24: Dyer | H24: callumjd@outlook.com | I24: Y | J24: WEBSITE | P24: =L24+M24+N24+O24 -> 0 | Q24: 121
B25: 45927 | C25: =CONCATENATE(D:D," ",E:E) -> Cara Mackley | D25: Cara | E25: Mackley | F25: Chesterfield Road | G25: TW152NE | H25: caramackley@hotmail.co.uk | I25: Y | J25: Sign Up Sheet | K25: 45957 | L25: 5 | N25: -0.45 | P25: =L25+M25+N25+O25 -> 4.55 | Q25: 204
B26: 45710 | C26: =CONCATENATE(D:D," ",E:E) -> Carol Kielty | D26: Carol | E26: Kielty | F26: Exford Avenue | G26: TW15 2EF | H26: jim.kielty@btinternet.com | I26: Y | J26: Sign Up Sheet | K26: 45776 | O26: 5 | P26: =L26+M26+N26+O26 -> 5 | Q26: 7
B27: 45710 | C27: =CONCATENATE(D:D," ",E:E) -> Carol Wooley | D27: Carol | E27: Wooley | G27: TW15 3BY | H27: k.e.woolley@btinternet.com | I27: Y | J27: Sign Up Sheet | P27: =L27+M27+N27+O27 -> 0 | Q27: 8
B28: 45766 | C28: =CONCATENATE(D:D," ",E:E) -> Carol Pringle | D28: Carol | E28: Pringle | H28: carol.gerald10@yahoo.co.uk | I28: Y | J28: EMAIL | P28: =L28+M28+N28+O28 -> 0 | Q28: 62
B29: 45710 | C29: =CONCATENATE(D:D," ",E:E) -> Carole Baxter | D29: Carole | E29: Baxter | G29: TW15 2SL | H29: cdandab23@gmail.com | I29: Y | J29: Sign Up Sheet | K29: 45825 | L29: 5 | N29: -0.45 | P29: =L29+M29+N29+O29 -> 4.55 | Q29: 9
B30: 45710 | C30: =CONCATENATE(D:D," ",E:E) -> Caroline Shannon | D30: Caroline | E30: Shannon | G30: TW15 2ND | H30: shannon.caroline@btinternet.com | I30: Y | J30: Sign Up Sheet | P30: =L30+M30+N30+O30 -> 0 | Q30: 10
B31: 45766 | C31: =CONCATENATE(D:D," ",E:E) -> Caroline Rogerson | D31: Caroline | E31: Rogerson | H31: carogerson57@yahoo.co.uk | I31: Y | J31: NEXTDOOR | P31: =L31+M31+N31+O31 -> 0 | Q31: 63
B32: 45909 | C32: =CONCATENATE(D:D," ",E:E) -> Caroline Toll | D32: Caroline | E32: Toll | F32: Woodthorpe Road | G32: TW15 2RU | H32: carolinetoll@hotmail.co.uk | I32: Y | J32: Website | P32: =L32+M32+N32+O32 -> 0 | Q32: 194
B33: 45822 | C33: =CONCATENATE(D:D," ",E:E) -> Cathy Waters | D33: Cathy | E33: Waters | F33: Fontmell Park | G33: TW15 2NW | H33: cjwatersuk@yahoo.co.uk | I33: Y | J33: Sign Up Sheet | P33: =L33+M33+N33+O33 -> 0 | Q33: 145
B34: 45934 | C34: =CONCATENATE(D:D," ",E:E) -> Charlotte Pope | D34: Charlotte | E34: Pope | F34: Ferndale Road | G34: TW153PJ | H34: beauport1066@gmail.com | I34: Y | J34: Website | P34: =L34+M34+N34+O34 -> 0 | Q34: 245
B35: 45939 | C35: =CONCATENATE(D:D," ",E:E) -> Charlotte Atkinson | D35: Charlotte | E35: Atkinson | F35: Coleridge Road | G35: TW15 2QS | H35: charlotteatkinson3@icloud.com | I35: Y | J35: FACEBOOK | K35: 45939 | L35: 5 | N35: -0.45 | P35: =L35+M35+N35+O35 -> 4.55 | Q35: 249
B36: 45766 | C36: =CONCATENATE(D:D," ",E:E) -> Chris Chattam | D36: Chris | E36: Chattam | H36: christine.chattam@gmail.com | I36: Y | J36: NEXTDOOR | P36: =L36+M36+N36+O36 -> 0 | Q36: 64
B37: 45710 | C37: =CONCATENATE(D:D," ",E:E) -> Christine Lloyd | D37: Christine | E37: Lloyd | G37: TW15 3ES | H37: c.lloyd01@btinternet.com | I37: Y | J37: Sign Up Sheet | P37: =L37+M37+N37+O37 -> 0 | Q37: 11
B38: 45710 | C38: =CONCATENATE(D:D," ",E:E) -> Christine Wooster | D38: Christine | E38: Wooster | G38: TW15 2PB | H38: chris.wooster@btinternet.com | I38: Y | J38: Sign Up Sheet | K38: 45826 | L38: 5 | N38: -0.45 | P38: =L38+M38+N38+O38 -> 4.55 | Q38: 12
B39: 45927 | C39: =CONCATENATE(D:D," ",E:E) -> Christine Sutcliffe | D39: Christine | E39: Sutcliffe | F39: Mayfield Close | G39: TW15 2AT | H39: wiss@live.co.uk | I39: Y | J39: Sign Up Sheet | P39: =L39+M39+N39+O39 -> 0 | Q39: 205
B40: 45941 | C40: =CONCATENATE(D:D," ",E:E) -> Christopher Salomons | D40: Christopher | E40: Salomons | F40: Coleridge Road | G40: TW15 2QS | H40: Chrisandvictoria1@gmail.com | I40: Y | J40: Website | P40: =L40+M40+N40+O40 -> 0 | Q40: 250
B41: 45813 | C41: =CONCATENATE(D:D," ",E:E) -> Clare Sabiston | D41: Clare | E41: Sabiston | F41: Church Road | G41: TW15 2UY | H41: Clareclareclares@gmail.com | I41: Y | J41: WEBSITE | P41: =L41+M41+N41+O41 -> 0 | Q41: 135
B42: 45820 | C42: =CONCATENATE(D:D," ",E:E) -> Colin Flack | D42: Colin | E42: Flack | F42: Village Way | G42: TW15 2JX | H42: Colin.e.flack@btinternet.com | I42: Y | J42: Leaflet | K42: 45820 | L42: 5 | N42: -0.45 | P42: =L42+M42+N42+O42 -> 4.55 | Q42: 139
B43: 45929 | C43: =CONCATENATE(D:D," ",E:E) -> Craig Hatton | D43: Craig | E43: Hatton | F43: Springfield Road | G43: TW15 2LR | H43: cjhatton13@gmail.com | I43: Y | J43: NHW | P43: =L43+M43+N43+O43 -> 0 | Q43: 231
B44: 45930 | C44: =CONCATENATE(D:D," ",E:E) -> Dan O’Sullivan | D44: Dan | E44: O’Sullivan | F44: Gables Avenue | G44: TW15 2TA | H44: Stonefm@yahoo.co.uk | I44: Y | J44: FACEBOOK | P44: =L44+M44+N44+O44 -> 0 | Q44: 232
B45: 45813 | C45: =CONCATENATE(D:D," ",E:E) -> Daniel Tomlinson | D45: Daniel | E45: Tomlinson | H45: dannytomlinson@yahoo.co.uk | I45: Y | J45: Leaflet | P45: =L45+M45+N45+O45 -> 0 | Q45: 136
B46: 45790 | C46: =CONCATENATE(D:D," ",E:E) -> Daphne & Martyn Tanner | D46: Daphne & Martyn | E46: Tanner | F46: Junction Rd | G46: TW15 1NQ | H46: daffers@gmail.com | I46: Y | J46: WEBSITE | K46: 45790 | L46: 5 | N46: -0.45 | P46: =L46+M46+N46+O46 -> 4.55 | Q46: 127
B47: 45766 | C47: =CONCATENATE(D:D," ",E:E) -> Dareen A | D47: Dareen | E47: A | H47: zany247@gmail.com | I47: Y | J47: NEXTDOOR | P47: =L47+M47+N47+O47 -> 0 | Q47: 65
B48: 45710 | C48: =CONCATENATE(D:D," ",E:E) -> David Lee | D48: David | E48: Lee | G48: TW15 3EU | H48: madlee01@yahoo.co.uk | I48: Y | J48: Sign Up Sheet | K48: 45985 | L48: 5 | N48: -0.45 | P48: =L48+M48+N48+O48 -> 4.55 | Q48: 14
B49: 45710 | C49: =CONCATENATE(D:D," ",E:E) -> David Small | D49: David | E49: Small | G49: TW15 2RR | H49: davidjsmall@btinternet.com | I49: Y | J49: Sign Up Sheet | P49: =L49+M49+N49+O49 -> 0 | Q49: 15
B50: 45806 | C50: =CONCATENATE(D:D," ",E:E) -> David Endersby | D50: David | E50: Endersby | F50: Chaucer Road | G50: TW15 2QT | H50: david@tw18businessmedia.co.uk | I50: Y | J50: FACEBOOK | K50: 45806 | L50: 5 | N50: -0.45 | P50: =L50+M50+N50+O50 -> 4.55 | Q50: 132
B51: 45907 | C51: =CONCATENATE(D:D," ",E:E) -> David Barham | D51: David | E51: Barham | F51: Orchard Close | G51: TW15 1JD | H51: davidbarham121@hotmail.co.uk | I51: Y | J51: Sign Up Sheet | P51: =L51+M51+N51+O51 -> 0 | Q51: 187
B52: 45710 | C52: =CONCATENATE(D:D," ",E:E) -> David & Tracey Outhwaite | D52: David & Tracey | E52: Outhwaite | G52: TW15 3JH | H52: davidouthwaite@hotmail.com | I52: Y | J52: Sign Up Sheet | P52: =L52+M52+N52+O52 -> 0 | Q52: 13
B53: 45778 | C53: =CONCATENATE(D:D," ",E:E) -> Deb Cousens | D53: Deb | E53: Cousens | F53: Chesterfield Road | G53: TW15 2ND | H53: debbie.cousens.dc@gmail.com | I53: Y | J53: Committee | P53: =L53+M53+N53+O53 -> 0 | Q53: 90 | R53: Committee Treasurer/Family Membership
B54: 45766 | C54: =CONCATENATE(D:D," ",E:E) -> Debbie Potter | D54: Debbie | E54: Potter | H54: debbierpotter@yahoo.co.uk | I54: Y | J54: EMAIL | P54: =L54+M54+N54+O54 -> 0 | Q54: 66
B55: 45822 | C55: =CONCATENATE(D:D," ",E:E) -> Deborah Nutt | D55: Deborah | E55: Nutt | F55: Anglesey Close | G55: TW15 2JU | H55: deborahnutt@btinternet.com | I55: Y | J55: Sign Up Sheet | P55: =L55+M55+N55+O55 -> 0 | Q55: 146
B56: 45780 | C56: =CONCATENATE(D:D," ",E:E) -> Debra McNeaney | D56: Debra | E56: McNeaney | F56: Ashgrove Road | G56: TW15 1NS | H56: debramcneaney@gmail.com | I56: Y | J56: WEBSITE | P56: =L56+M56+N56+O56 -> 0 | Q56: 101
B57: 45710 | C57: =CONCATENATE(D:D," ",E:E) -> Dennis & Joan Leeks | D57: Dennis & Joan | E57: Leeks | G57: TW15 3SB | H57: d&jLeeks@btinternet.com | I57: Y | J57: Sign Up Sheet | P57: =L57+M57+N57+O57 -> 0 | Q57: 16
B58: 45927 | C58: =CONCATENATE(D:D," ",E:E) -> Derek Scott | D58: Derek | E58: Scott | F58: Chaucer Road | G58: TW15 2QU | I58: Y | J58: Sign Up Sheet | P58: =L58+M58+N58+O58 -> 0 | Q58: 206
B59: 45932 | C59: =CONCATENATE(D:D," ",E:E) -> Dhiren Kanojiya | D59: Dhiren | E59: Kanojiya | F59: Lucie Avenue | G59: TW15 2BH | H59: dhirenk@outlook.com | I59: Y | J59: Website | P59: =L59+M59+N59+O59 -> 0 | Q59: 243
B60: 45822 | C60: =CONCATENATE(D:D," ",E:E) -> Diana Lloyd | D60: Diana | E60: Lloyd | F60: Exeforde Avenue | G60: TW15 2EF | H60: diana.e.lloyd@hotmail.com | I60: Y | J60: Sign Up Sheet | P60: =L60+M60+N60+O60 -> 0 | Q60: 147
B61: 45782 | C61: =CONCATENATE(D:D," ",E:E) -> Diane Clark | D61: Diane | E61: Clark | F61: Brownrigg Road | G61: TW15 2TL | H61: dianeclark.swb@yahoo.com | I61: Y | J61: WEBSITE | K61: 45826 | L61: 5 | N61: -0.45 | P61: =L61+M61+N61+O61 -> 4.55 | Q61: 122
B62: 45780 | C62: =CONCATENATE(D:D," ",E:E) -> Dominic Winterburn | D62: Dominic | E62: Winterburn | F62: Feltham Hill Road | G62: TW15 1LU | H62: dominicsfishing@hotmail.com | I62: Y | J62: WEBSITE | P62: =L62+M62+N62+O62 -> 0 | Q62: 102
B63: 45807 | C63: =CONCATENATE(D:D," ",E:E) -> Elaine Emmerton | D63: Elaine | E63: Emmerton | F63: Desford Way | G63: TW15 3AR | H63: elaine@metrayfinancials.co.uk | I63: Y | J63: FACEBOOK | K63: 45825 | L63: 5 | N63: -0.45 | P63: =L63+M63+N63+O63 -> 4.55 | Q63: 133
B64: 45822 | C64: =CONCATENATE(D:D," ",E:E) -> Ernst Bachmann | D64: Ernst | E64: Bachmann | F64: Parklane Grove | G64: TW15 2JF | H64: ernstbach@aol.com | I64: Y | J64: Sign Up Sheet | P64: =L64+M64+N64+O64 -> 0 | Q64: 148
B65: 45822 | C65: =CONCATENATE(D:D," ",E:E) -> Evelyn Mitchell | D65: Evelyn | E65: Mitchell | F65: Hawley Way | G65: TW15 2EN | H65: evelynmitchell@hotmail.co.uk | I65: Y | J65: Sign Up Sheet | P65: =L65+M65+N65+O65 -> 0 | Q65: 149
B66: 45820 | C66: =CONCATENATE(D:D," ",E:E) -> Farhad ? | D66: Farhad | E66: ? | F66: Village way | G66: TW15 2LB | H66: Farhad_uk@yahoo.co.uk | I66: Y | J66: Leaflet | P66: =L66+M66+N66+O66 -> 0 | Q66: 140
B67: 45822 | C67: =CONCATENATE(D:D," ",E:E) -> Francesca Parsons | D67: Francesca | E67: Parsons | F67: Denman Drive | G67: TW15 2AP | H67: fparsons4@hotmail.com | I67: Y | J67: Sign Up Sheet | K67: 45827 | L67: 5 | M67: 5 | N67: -0.9 | P67: =L67+M67+N67+O67 -> 9.1 | Q67: 150 | R67: Paid £5 donation + membership
B68: 45710 | C68: =CONCATENATE(D:D," ",E:E) -> Frank & Laura Greaves | D68: Frank & Laura | E68: Greaves | G68: TW15 3JU | H68: fandlgreaves@gmail.com | I68: Y | J68: Sign Up Sheet | P68: =L68+M68+N68+O68 -> 0 | Q68: 17
B69: 45907 | C69: =CONCATENATE(D:D," ",E:E) -> Gabriella Marsalla | D69: Gabriella | E69: Marsalla | F69: Orchard Close | G69: TW15 1JD | H69: marsgabi@hotmail.co.uk | I69: Y | J69: Sign Up Sheet | P69: =L69+M69+N69+O69 -> 0 | Q69: 188
B70: 45744 | C70: =CONCATENATE(D:D," ",E:E) -> Gareth Williams | D70: Gareth | E70: Williams | H70: gareth.jon.williams@gmail.com | I70: Y | J70: NHW | P70: =L70+M70+N70+O70 -> 0 | Q70: 51
B71: 45825 | C71: =CONCATENATE(D:D," ",E:E) -> Gareth Williams | D71: Gareth | E71: Williams | F71: Parkland Grove | G71: TW15 2JB | H71: gareth.williams@gurglephut.com | I71: Y | J71: FACEBOOK | K71: 45825 | L71: 5 | N71: -0.45 | P71: =L71+M71+N71+O71 -> 4.55 | Q71: 174
B72: 45822 | C72: =CONCATENATE(D:D," ",E:E) -> Gary Waters | D72: Gary | E72: Waters | F72: Fontmell Park | G72: TW15 2NW | H72: gswatersuk@yahoo.co.uk | I72: Y | J72: Sign Up Sheet | P72: =L72+M72+N72+O72 -> 0 | Q72: 151
B73: 45710 | C73: =CONCATENATE(D:D," ",E:E) -> Geoffrey Rippingale | D73: Geoffrey | E73: Rippingale | G73: TW15 2SN | H73: gripp@btinternet.com | I73: Y | J73: Sign Up Sheet | P73: =L73+M73+N73+O73 -> 0 | Q73: 18
B74: 45769 | C74: =CONCATENATE(D:D," ",E:E) -> Glen Watson | D74: Glen | E74: Watson | H74: glenn.watson@ashfordrevive.org | I74: Y | J74: EMAIL | P74: =L74+M74+N74+O74 -> 0 | Q74: 70
B75: 45744 | C75: =CONCATENATE(D:D," ",E:E) -> Gordon Briggs | D75: Gordon | E75: Briggs | F75: Salcome Road | G75: TW15 3BS | H75: gordon.briggs@hotmail.co.uk | I75: Y | J75: Sign Up Sheet | P75: =L75+M75+N75+O75 -> 0 | Q75: 52
B76: 45781 | C76: =CONCATENATE(D:D," ",E:E) -> Graham Lawson | D76: Graham | E76: Lawson | H76: grahamontowlawson@gmail.com | I76: Y | J76: WEBSITE | P76: =L76+M76+N76+O76 -> 0 | Q76: 118
B77: 45710 | C77: =CONCATENATE(D:D," ",E:E) -> Greg Neall | D77: Greg | E77: Neall | G77: TW15 1LR | H77: greg@wakeupyourwealth.com | I77: Y | J77: Sign Up Sheet | P77: =L77+M77+N77+O77 -> 0 | Q77: 19
B78: 45873 | C78: =CONCATENATE(D:D," ",E:E) -> Gurpinder Johal | D78: Gurpinder | E78: Johal | F78: Gilmore Crescent | G78: TW15 2DB | H78: gurpinderjohal@icloud.com | I78: Y | J78: Website | P78: =L78+M78+N78+O78 -> 0 | Q78: 180
B79: 45907 | C79: =CONCATENATE(D:D," ",E:E) -> Gush Bhullar | D79: Gush | E79: Bhullar | F79: Saxon Road | G79: TW15 1QL | H79: gushbhullar1@gmail.com | I79: Y | J79: Sign Up Sheet | P79: =L79+M79+N79+O79 -> 0 | Q79: 189
B80: 45777 | C80: =CONCATENATE(D:D," ",E:E) -> Heather McIntyre | D80: Heather | E80: McIntyre | F80: Mornington Road | G80: TW15 1NW | H80: heathermcintyre28@btinternet.com | I80: Y | J80: Sign Up Sheet | P80: =L80+M80+N80+O80 -> 0 | Q80: 84
B81: 45822 | C81: =CONCATENATE(D:D," ",E:E) -> Heather Wasley | D81: Heather | E81: Wasley | F81: Chesterfield Road | G81: TW15 2ND | H81: hwasley@googlemail.com | I81: Y | J81: Sign Up Sheet | P81: =L81+M81+N81+O81 -> 0 | Q81: 152
B82: 45710 | C82: =CONCATENATE(D:D," ",E:E) -> Helen Collis | D82: Helen | E82: Collis | G82: TW15 2QX | H82: collid2@virginmedia.com | I82: Y | J82: Sign Up Sheet | K82: 45991 | L82: 5 | N82: -0.45 | P82: =L82+M82+N82+O82 -> 4.55 | Q82: 20
B83: 45710 | C83: =CONCATENATE(D:D," ",E:E) -> Helen Mason | D83: Helen | E83: Mason | G83: TW15 2HF | H83: helenlmason@hotmail.co.uk | I83: Y | J83: Sign Up Sheet | P83: =L83+M83+N83+O83 -> 0 | Q83: 21
B84: 45822 | C84: =CONCATENATE(D:D," ",E:E) -> Helen Beecham | D84: Helen | E84: Beecham | F84: Feltham Hill Road | G84: TW15 1LN | H84: helenbeecham@gmail.com | I84: Y | J84: Sign Up Sheet | P84: =L84+M84+N84+O84 -> 0 | Q84: 153
B85: 45927 | C85: =CONCATENATE(D:D," ",E:E) -> Helen Barker | D85: Helen | E85: Barker | F85: Cheserfield Road | G85: TW15 2NE | H85: helenbarker@gmail.com | I85: Y | J85: Sign Up Sheet | P85: =L85+M85+N85+O85 -> 0 | Q85: 207
B86: 45822 | C86: =CONCATENATE(D:D," ",E:E) -> Howard Wooton | D86: Howard | E86: Wooton | F86: Wolsey Road | G86: TW15 2RD | H86: wooton.family@btinternet.com | I86: Y | J86: Sign Up Sheet | P86: =L86+M86+N86+O86 -> 0 | Q86: 154
B87: 45927 | C87: =CONCATENATE(D:D," ",E:E) -> Ian Kirkby | D87: Ian | E87: Kirkby | F87: Dudley Road | G87: TW15 2LF | H87: ian5kirby@btinternet.com | I87: Y | J87: Sign Up Sheet | L87: 0 | N87: 0 | P87: =L87+M87+N87+O87 -> 0 | Q87: 208 | R87: Family Membership
B88: 45791 | C88: =CONCATENATE(D:D," ",E:E) -> Irene Brien | D88: Irene | E88: Brien | H88: j.brien@sky.com | I88: Y | J88: NHW | K88: 45788 | L88: 5 | N88: -0.45 | P88: =L88+M88+N88+O88 -> 4.55 | Q88: 129
B89: 45765 | C89: =CONCATENATE(D:D," ",E:E) -> Irfan Younas | D89: Irfan | E89: Younas | F89: Parkland Grove | G89: TW15 2JR | H89: miyounas@gmail.com | I89: Y | J89: Sign Up Sheet | P89: =L89+M89+N89+O89 -> 0 | Q89: 61
B90: 45771 | C90: =CONCATENATE(D:D," ",E:E) -> Isabelle Kielty | D90: Isabelle | E90: Kielty | F90: Arlington Road | G90: TW15 2LS | H90: i.kielts2006@gmail.com | I90: Y | J90: FR&FM | L90: 0 | N90: 0 | P90: =L90+M90+N90+O90 -> 0 | Q90: 72 | R90: Family Membership
B91: 45710 | C91: =CONCATENATE(D:D," ",E:E) -> Jackie & Les Brown | D91: Jackie & Les | E91: Brown | G91: TW15 3BX | H91: lesandjackiebrown@hotmail.co.uk | I91: Y | J91: Sign Up Sheet | P91: =L91+M91+N91+O91 -> 0 | Q91: 23
B92: 45771 | C92: =CONCATENATE(D:D," ",E:E) -> Jamieson Kielty | D92: Jamieson | E92: Kielty | F92: Brownrigg Road | G92: TW15 2TL | H92: jamieson.kielty@hotmail.co.uk | I92: Y | J92: FR&FM | L92: 0 | N92: 0 | P92: =L92+M92+N92+O92 -> 0 | Q92: 73 | R92: Family Membership
B93: 45822 | C93: =CONCATENATE(D:D," ",E:E) -> Jan Sivelle | D93: Jan | E93: Sivelle | F93: Village Way | G93: TW15 2LB | H93: jansivelle@hotmail.com | I93: Y | J93: Sign Up Sheet | P93: =L93+M93+N93+O93 -> 0 | Q93: 155
B94: 45710 | C94: =CONCATENATE(D:D," ",E:E) -> Jane Dobbie | D94: Jane | E94: Dobbie | G94: TW15 255 | H94: jane@padcroft.org | I94: Y | J94: Sign Up Sheet | P94: =L94+M94+N94+O94 -> 0 | Q94: 24
B95: 45776 | C95: =CONCATENATE(D:D," ",E:E) -> Jane Smith | D95: Jane | E95: Smith | H95: smith-j90@sky.com | I95: Y | J95: Sign Up Sheet | P95: =L95+M95+N95+O95 -> 0 | Q95: 79
B96: 45927 | C96: =CONCATENATE(D:D," ",E:E) -> Jane Whiting | D96: Jane | E96: Whiting | F96: Wellington Road | G96: TW15 3RT | H96: whiting562@gmail.com | I96: Y | J96: Sign Up Sheet | P96: =L96+M96+N96+O96 -> 0 | Q96: 209
B97: 45780 | C97: =CONCATENATE(D:D," ",E:E) -> Jane-Louise Taberer | D97: Jane-Louise | E97: Taberer | F97: Ashgrove Road | G97: TW15 1NU | H97: jltaberer@gmail.com | I97: Y | J97: WEBSITE | P97: =L97+M97+N97+O97 -> 0 | Q97: 103
B98: 45890 | C98: =CONCATENATE(D:D," ",E:E) -> Janet O’Brien | D98: Janet | E98: O’Brien | F98: Stanley Road | G98: TW15 2LW | H98: jjanetobrien@gmail.com | I98: Y | J98: WEBSITE | P98: =L98+M98+N98+O98 -> 0 | Q98: 182
B99: 45780 | C99: =CONCATENATE(D:D," ",E:E) -> Janice Stuart | D99: Janice | E99: Stuart | F99: Echleford Drive | G99: TW15 2ER | H99: jstuart@kingston.eu | I99: Y | J99: WEBSITE | P99: =L99+M99+N99+O99 -> 0 | Q99: 104
B100: 45710 | C100: =CONCATENATE(D:D," ",E:E) -> Jean Parry | D100: Jean | E100: Parry | G100: TW15 2DE | H100: jicparry@aol.com | I100: Y | J100: Sign Up Sheet | P100: =L100+M100+N100+O100 -> 0 | Q100: 22
...
